Workbook

Sheet Cover
B2: MAX HEALTHCARE INSTITUTE LTD (MAXHEALTH)
B3: Integrated Financial Model & Equity Research | FY20A-FY26A actuals, FY27E-FY33E forecast
B4: Units: INR Crore (1 Cr = 100 lakh) unless stated. Consolidated financials. Prepared Jul-2026.
B6: RECOMMENDATION
B7: Rating | C7: BUY / ACCUMULATE
B8: Current price (Rs) | C8: ='Assumptions'!I43
B9: Target price - SoTP/Relative blend (Rs) | C9: ='SoTP Street'!C32 | D9: ='SoTP Street'!C32/'Assumptions'!I43-1
B10: SoTP target (12M fwd, FY28E) | C10: ='SoTP Street'!C23
B11: Relative EV/EBITDA / P/E (Rs) | C11: ='Relative Valuation'!C17 | D11: ='Relative Valuation'!C19
B12: DCF: exit-multiple / Gordon (Rs) | C12: ='DCF'!C38 | D12: ='DCF'!C33
B13: Street consensus BUY, avg Rs 1,148 (26 analysts). Primary methodology = forward EV/EBITDA / SoTP (sector norm); Gordon DCF (~Rs590) is the downside/valuation-risk anchor.
B15: KEY FINANCIALS (Rs Cr)
C16: FY26A | D16: FY30E | E16: FY33E
B17: Revenue | C17: ='Integrated IS'!H5 | D17: ='Integrated IS'!L5 | E17: ='Integrated IS'!O5
B18: EBITDA | C18: ='Integrated IS'!H13 | D18: ='Integrated IS'!L13 | E18: ='Integrated IS'!O13
B19: PAT | C19: ='Integrated IS'!H25 | D19: ='Integrated IS'!L25 | E19: ='Integrated IS'!O25
B20: EPS (Rs) | C20: ='Integrated IS'!H27 | D20: ='Integrated IS'!L27 | E20: ='Integrated IS'!O27
B22: WACC | C22: ='DCF'!C14
B23: Terminal growth | C23: ='Assumptions'!I42
B24: Credit rating (CARE) | C24: AA+ / Stable
B26: CONTENTS
B27: 1 Cover
B28: 2 Historical P&L
B29: 3 Historical BS
B30: 4 Historical CF
B31: 5 Historical Notes
B32: 6 Historical KPIs
B33: 7 Assumptions
B34: 8-11 Operating model (Beds/Occupancy/ARPOB/Revenue)
B35: 12 Direct Cost & GP
B36: 13 Opex
B37: 14 EBITDA
... B53: 30 Model Checks

Sheet Historical P&L
A1: 2. HISTORICAL CONSOLIDATED STATEMENT OF PROFIT & LOSS (FY20A-FY26A)
A3: Source: Consolidated P&L, Max Healthcare Annual Reports FY21-FY26 (reported in INR lakh; shown in INR Crore = lakh/100). Reported classification preserved.
A4: INR Crore unless stated | B4: FY20A | C4: FY21A | D4: FY22A | E4: FY23A | F4: FY24A | G4: FY25A | H4: FY26A | I4: FY27E | J4: FY28E | K4: FY29E | L4: FY30E | M4: FY31E | N4: FY32E | O4: FY33E
A5: Revenue from operations | B5: 1059.03 | C5: 2504.67 | D5: 3936.55 | E5: 4562.6 | F5: 5406.02 | G5: 7028.46 | H5: 8373.45
A6: Other income | B6: 48.08 | C6: 114.74 | D6: 122.27 | E6: 139.24 | F6: 176.94 | G6: 155.64 | H6: 162.62
A7: Total income | B7: =B5+B6 | C7: =C5+C6 | D7: =D5+D6 | E7: =E5+E6 | F7: =F5+F6 | G7: =G5+G6 | H7: =H5+H6
A8: Expenses
A9: Purchase of drugs, consumables & implants | B9: 229.35 | C9: 580.51 | D9: 930.46 | E9: 936.88 | F9: 1119.04 | G9: 1496.41 | H9: 1798.75
A10: Change in inventories | B10: -12.04 | C10: 13.9 | D10: -7.56 | E10: -14.87 | F10: -0.52 | G10: -19.36 | H10: -8.73
A11: Employee benefits expense | B11: 230.13 | C11: 588.78 | D11: 759.92 | E11: 809.35 | F11: 934.4 | G11: 1174.01 | H11: 1357.12
A12: Professional & consultancy fee | B12: 246.94 | C12: 532.91 | D12: 809.45 | E12: 986.31 | F12: 1116.89 | G12: 1474.7 | H12: 1794.01
A13: Other expenses | B13: 271.07 | C13: 384.71 | D13: 496.63 | E13: 604.4 | F13: 742.96 | G13: 1053.9 | H13: 1189.47
A14: Finance costs | B14: 83.24 | C14: 179.46 | D14: 100.87 | E14: 83.86 | F14: 59.89 | G14: 165.02 | H14: 235.1
A15: Depreciation & amortisation | B15: 45.64 | C15: 174.09 | D15: 221.12 | E15: 232.19 | F15: 244.98 | G15: 359.42 | H15: 446.53
A16: Total expenses | B16: =B9+B10+B11+B12+B13+B14+B15 | C16: =C9+C10+C11+C12+C13+C14+C15 | D16: =D9+D10+D11+D12+D13+D14+D15 | E16: =E9+E10+E11+E12+E13+E14+E15 | F16: =F9+F10+F11+F12+F13+F14+F15 | G16: =G9+G10+G11+G12+G13+G14+G15 | H16: =H9+H10+H11+H12+H13+H14+H15
A17: Profit before exceptional items & tax | B17: =B7-B16 | C17: =C7-C16 | D17: =D7-D16 | E17: =E7-E16 | F17: =F7-F16 | G17: =G7-G16 | H17: =H7-H16
A18: Exceptional items | B18: 0 | C18: -233.7 | D18: -9.03 | E18: 0 | F18: 0 | G18: -73.63 | H18: -48.24
A19: Profit before tax | B19: =B17+B18 | C19: =C17+C18 | D19: =D17+D18 | E19: =E17+E18 | F19: =F17+F18 | G19: =G17+G18 | H19: =H17+H18
A20: Total tax expense | B20: -0.13 | C20: 45.85 | D20: 133.85 | E20: -39.79 | F20: 307.68 | G20: 330.49 | H20: 233.17
A21: Profit after tax (before assoc.) | B21: =B19-B20 | C21: =C19-C20 | D21: =D19-D20 | E21: =E19-E20 | F21: =F19-F20 | G21: =G19-G20 | H21: =H19-H20
A22: Share of profit/(loss) in associate | B22: 46.08 | C22: -23.05 | D22: 0 | E22: 0 | F22: 0 | G22: 0 | H22: 0
A23: Profit for the year (PAT) | B23: =B21+B22 | C23: =C21+C22 | D23: =D21+D22 | E23: =E21+E22 | F23: =F21+F22 | G23: =G21+G22 | H23: =H21+H22
A24: Analytical memo (calculated)
A25: Direct cost (drugs + chg. inventory) | B25: =B9+B10 | C25: =C9+C10 | D25: =D9+D10 | E25: =E9+E10 | F25: =F9+F10 | G25: =G9+G10 | H25: =H9+H10
A26: Analytical Gross Profit | B26: =B5-B25 | C26: =C5-C25 | D26: =D5-D25 | E26: =E5-E25 | F26: =F5-F25 | G26: =G5-G25 | H26: =H5-H25
A27: Analytical Gross Margin % | B27: =B26/B5 | C27: =C26/C5 | D27: =D26/D5 | E27: =E26/E5 | F27: =F26/F5 | G27: =G26/G5 | H27: =H26/H5
A28: EBITDA (excl. other income) | B28: =B26-B11-B12-B13 | C28: =C26-C11-C12-C13 | D28: =D26-D11-D12-D13 | E28: =E26-E11-E12-E13 | F28: =F26-F11-F12-F13 | G28: =G26-G11-G12-G13 | H28: =H26-H11-H12-H13
A29: EBITDA Margin % | B29: =B28/B5 | C29: =C28/C5 | D29: =D28/D5 | E29: =E28/E5 | F29: =F28/F5 | G29: =G28/G5 | H29: =H28/H5
A30: PBIDT (EBITDA + other income) | B30: =B28+B6 | C30: =C28+C6 | D30: =D28+D6 | E30: =E28+E6 | F30: =F28+F6 | G30: =G28+G6 | H30: =H28+H6
A31: Revenue growth % | C31: =C5/B5-1 | D31: =D5/C5-1 | E31: =E5/D5-1 | F31: =F5/E5-1 | G31: =G5/F5-1 | H31: =H5/G5-1
A32: PAT margin % | B32: =B23/B5 | C32: =C23/C5 | D32: =D23/D5 | E32: =E23/E5 | F32: =F23/F5 | G32: =G23/G5 | H32: =H23/H5
A34: Note: FY20A represents Radiant Life Care (accounting acquirer under reverse acquisition, Ind AS 103); FY21A includes 10 months of MHIL + 12 months of Radiant. FY20-FY21 are NOT strictly comparable with FY22A onwards.

Sheet Historical BS
A1: 3. HISTORICAL CONSOLIDATED BALANCE SHEET (FY20A-FY26A)
A3: Source: Consolidated Balance Sheet, Annual Reports FY21-FY26 (INR lakh -> Crore). Reported classification preserved.
A4: INR Crore unless stated | B4: FY20A | C4: FY21A | D4: FY22A | E4: FY23A | F4: FY24A | G4: FY25A | H4: FY26A | I4: FY27E | J4: FY28E | K4: FY29E | L4: FY30E | M4: FY31E | N4: FY32E | O4: FY33E
A5: ASSETS - Non-current assets
A6: Property, plant & equipment | B6: 274.56 | C6: 1522.71 | D6: 1732.57 | E6: 1829.22 | F6: 2578.2 | G6: 4130.88 | H6: 5628
A7: Right-of-use assets | B7: 16.21 | C7: 225.48 | D7: 221.01 | E7: 189.86 | F7: 667.63 | G7: 1331.05 | H7: 1351.96
A8: Capital work-in-progress | B8: 27.55 | C8: 26.72 | D8: 104.73 | E8: 206.55 | F8: 445.25 | G8: 900.45 | H8: 592.24
A9: Investment property | B9: 0 | C9: 0 | D9: 0 | E9: 0 | F9: 63.03 | G9: 4.66 | H9: 4.66
A10: Goodwill | B10: 417.58 | C10: 2454.66 | D10: 2454.66 | E10: 2454.66 | F10: 2952.47 | G10: 3480.26 | H10: 3488.24
A11: Other intangible assets | B11: 142.6 | C11: 2333.53 | D11: 2609.34 | E11: 2564.96 | F11: 2522.36 | G11: 2554.74 | H11: 2518.2
A12: Intangible assets under development | B12: 0 | C12: 0.21 | D12: 46.39 | E12: 45.88 | F12: 107.79 | G12: 0.27 | H12: 0.81
A13: Investments (non-current) | B13: 0 | C13: 0.51 | D13: 0.51 | E13: 0.51 | F13: 2.12 | G13: 2.89 | H13: 5.46
A14: Trade receivables (non-current) | B14: 0 | C14: 119.45 | D14: 107.73 | E14: 102.84 | F14: 96.56 | G14: 88.75 | H14: 79.15
A15: Loans (non-current) | B15: 2.84 | C15: 356.99 | D15: 173.45 | E15: 138.45 | F15: 138.45 | G15: 383.45 | H15: 746.45
A16: Other financial assets (non-current) | B16: 2.46 | C16: 2.41 | D16: 275.78 | E16: 206.03 | F16: 230.14 | G16: 204.04 | H16: 203.91
A17: Income tax assets (net) | B17: 65.45 | C17: 155.33 | D17: 155.17 | E17: 95.72 | F17: 125.24 | G17: 138.28 | H17: 264.05
... A19: Other non-current assets | B19: 109.02 | C19: 220.99 | D19: 307.5 | E19: 324.1 | F19: 364.52 | G19: 374.15 | H19: 356.53
A20: Total non-current assets | B20: =B6+B7+B8+B9+B10+B11+B12+B13+B14+B15+B16+B17+B18+B19 | C20: =C6+C7+C8+C9+C10+C11+C12+C13+C14+C15+C16+C17+C18+C19 | D20: =D6+D7+D8+D9+D10+D11+D12+D13+D14+D15+D16+D17+D18+D19 | E20: =E6+E7+E8+E9+E10+E11+E12+E13+E14+E15+E16+E17+E18+E19 | F20: =F6+F7+F8+F9+F10+F11+F12+F13+F14+F15+F16+F17+F18+F19 | G20: =G6+G7+G8+G9+G10+G11+G12+G13+G14+G15+G16+G17+G18+G19 | H20: =H6+H7+H8+H9+H10+H11+H12+H13+H14+H15+H16+H17+H18+H19
A21: Current assets
A22: Inventories | B22: 26.8 | C22: 53.8 | D22: 61.36 | E22: 76.23 | F22: 79.84 | G22: 106.21 | H22: 114.28
A23: Investments (current) | B23: 2182.06 | C23: 0 | D23: 0 | E23: 0 | F23: 0 | G23: 0 | H23: 0
A24: Trade receivables (current) | B24: 96.09 | C24: 365.89 | D24: 385.36 | E24: 336.12 | F24: 462.69 | G24: 687.31 | H24: 969.75
A25: Cash & cash equivalents | B25: 111.01 | C25: 626.59 | D25: 309.14 | E25: 42.75 | F25: 979.84 | G25: 661.58 | H25: 665.8
A26: Bank balances other than above | B26: 8.56 | C26: 26.33 | D26: 190.17 | E26: 1425.32 | F26: 119.43 | G26: 20.31 | H26: 34.8
A27: Loans (current) | B27: 452.69 | C27: 5.43 | D27: 2.58 | E27: 0 | F27: 0 | G27: 10.37 | H27: 0
A28: Other financial assets (current) | B28: 17.61 | C28: 21.91 | D28: 30.1 | E28: 30.54 | F28: 41.34 | G28: 58.14 | H28: 70.57
A29: Income tax assets (net, current) | B29: 10.9 | C29: 6.61 | D29: 0 | E29: 15.78 | F29: 3.92 | G29: 0 | H29: 34.8
A30: Other current assets | B30: 9.67 | C30: 17.91 | D30: 21.58 | E30: 16.33 | F30: 19.12 | G30: 48.65 | H30: 54.79
A31: Total current assets | B31: =B22+B23+B24+B25+B26+B27+B28+B29+B30 | C31: =C22+C23+C24+C25+C26+C27+C28+C29+C30 | D31: =D22+D23+D24+D25+D26+D27+D28+D29+D30 | E31: =E22+E23+E24+E25+E26+E27+E28+E29+E30 | F31: =F22+F23+F24+F25+F26+F27+F28+F29+F30 | G31: =G22+G23+G24+G25+G26+G27+G28+G29+G30 | H31: =H22+H23+H24+H25+H26+H27+H28+H29+H30
A32: TOTAL ASSETS | B32: =B20+B31 | C32: =C20+C31 | D32: =D20+D31 | E32: =E20+E31 | F32: =F20+F31 | G32: =G20+G31 | H32: =H20+H31
A33: EQUITY & LIABILITIES - Equity
A34: Equity share capital | B34: 537.24 | C34: 965.95 | D34: 969.61 | E34: 970.92 | F34: 971.91 | G34: 972.14 | H34: 973.13
A35: Other equity | B35: 2015.91 | C35: 4672.73 | D35: 5312.86 | E35: 6438.67 | F35: 7436.23 | G35: 8408.73 | H35: 9773.5
A36: Total equity | B36: =B34+B35 | C36: =C34+C35 | D36: =D34+D35 | E36: =E34+E35 | F36: =F34+F35 | G36: =G34+G35 | H36: =H34+H35
A37: Non-current liabilities
A38: Borrowings | B38: 106.23 | C38: 842.82 | D38: 629.41 | E38: 496.58 | F38: 1060.83 | G38: 2270.06 | H38: 2438.66
A39: Lease liabilities | B39: 14.45 | C39: 169.99 | D39: 170.17 | E39: 107.88 | F39: 127.64 | G39: 497.55 | H39: 539.32
A40: Other financial liabilities | B40: 241.89 | C40: 237.26 | D40: 378.5 | E40: 319.57 | F40: 340.05 | G40: 272.35 | H40: 268.57
A41: Provisions | B41: 40.66 | C41: 60.19 | D41: 59.79 | E41: 60.48 | F41: 75.47 | G41: 98.07 | H41: 127.82
A42: Deferred tax liabilities (net) | B42: 0 | C42: 581.92 | D42: 681.41 | E42: 437.13 | F42: 514.85 | G42: 648.19 | H42: 687.53
A43: Other non-current liabilities | B43: 7.33 | C43: 236.65 | D43: 230.11 | E43: 225.05 | F43: 224.25 | G43: 233.62 | H43: 235.47
A44: Total non-current liabilities | B44: =B38+B39+B40+B41+B42+B43 | C44: =C38+C39+C40+C41+C42+C43 | D44: =D38+D39+D40+D41+D42+D43 | E44: =E38+E39+E40+E41+E42+E43 | F44: =F38+F39+F40+F41+F42+F43 | G44: =G38+G39+G40+G41+G42+G43 | H44: =H38+H39+H40+H41+H42+H43
A45: Current liabilities
A46: Borrowings | B46: 727.37 | C46: 54.25 | D46: 97.24 | E46: 68.24 | F46: 88.79 | G46: 218.77 | H46: 468.16
A47: Lease liabilities | B47: 5.13 | C47: 11.07 | D47: 16.56 | E47: 16.26 | F47: 21.69 | G47: 23.91 | H47: 32.22
A48: Trade payables | B48: 179.63 | C48: 435.69 | D48: 444.11 | E48: 543.46 | F48: 633.01 | G48: 807.92 | H48: 859.04
A49: Other financial liabilities | B49: 56.19 | C49: 181.99 | D49: 92.53 | E49: 284.56 | F49: 326.06 | G49: 521.81 | H49: 572.53
A50: Other current liabilities | B50: 33.94 | C50: 54.5 | D50: 65.15 | E50: 84.68 | F50: 118.01 | G50: 162.53 | H50: 173.56
A51: Provisions | B51: 7.69 | C51: 39.43 | D51: 41.68 | E51: 48.37 | F51: 61.15 | G51: 78.83 | H51: 81.43
A52: Total current liabilities | B52: =B46+B47+B48+B49+B50+B51 | C52: =C46+C47+C48+C49+C50+C51 | D52: =D46+D47+D48+D49+D50+D51 | E52: =E46+E47+E48+E49+E50+E51 | F52: =F46+F47+F48+F49+F50+F51 | G52: =G46+G47+G48+G49+G50+G51 | H52: =H46+H47+H48+H49+H50+H51
A53: Total liabilities | B53: =B44+B52 | C53: =C44+C52 | D53: =D44+D52 | E53: =E44+E52 | F53: =F44+F52 | G53: =G44+G52 | H53: =H44+H52
A54: TOTAL EQUITY & LIABILITIES | B54: =B36+B53 | C54: =C36+C53 | D54: =D36+D53 | E54: =E36+E53 | F54: =F36+F53 | G54: =G36+G53 | H54: =H36+H53
A55: Balance check (Assets - E&L) | B55: =B32-B54 | C55: =C32-C54 | D55: =D32-D54 | E55: =E32-E54 | F55: =F32-F54 | G55: =G32-G54 | H55: =H32-H54

Sheet Historical CF
A1: 4. HISTORICAL CONSOLIDATED CASH FLOW STATEMENT (FY20A-FY26A)
A3: Source: Consolidated Cash Flow Statement, Annual Reports FY21-FY26 (INR lakh -> Crore). Summary presentation.
A4: INR Crore unless stated | B4: FY20A | C4: FY21A | D4: FY22A | E4: FY23A | F4: FY24A | G4: FY25A | H4: FY26A | I4: FY27E | J4: FY28E | K4: FY29E | L4: FY30E | M4: FY31E | N4: FY32E | O4: FY33E
A5: Net cash from operating activities | B5: 77.09 | C5: 117.86 | D5: 740.52 | E5: 1209.18 | F5: 1121.67 | G5: 1437.96 | H5: 1633.32
A6: of which: Capex (PP&E, intangibles, CWIP) | B6: -90.09 | C6: -118.42 | D6: -553.34 | E6: -335.61 | F6: -785.95 | G6: -944.48 | H6: -1484.53
A7: Net cash used in investing activities | B7: -2640.7 | C7: -73 | D7: -763.8 | E7: -1187.01 | F7: -1285.45 | G7: -1610.69 | H7: -1688.99
A8: of which: Dividends paid | B8: 0 | C8: 0 | D8: 0 | E8: 0 | F8: -97.01 | G8: -145.58 | H8: -145.62
A9: Net cash from/(used in) financing activities | B9: 2353.12 | C9: 191.33 | D9: -294.17 | E9: -288.56 | F9: -263.74 | G9: -163.16 | H9: 59.27
A10: Net increase/(decrease) in cash | B10: =B5+B7+B9 | C10: =C5+C7+C9 | D10: =D5+D7+D9 | E10: =E5+E7+E9 | F10: =F5+F7+F9 | G10: =G5+G7+G9 | H10: =H5+H7+H9
A11: Opening cash & cash equivalents | B11: 321.5 | C11: 111.01 | D11: 626.59 | E11: 309.14 | F11: 42.75 | G11: 979.84 | H11: 661.58
A12: Closing cash & cash equivalents | B12: =B11+B10 | C12: =C11+C10 | D12: =D11+D10 | E12: =E11+E10 | F12: =F11+F10 | G12: =G11+G10 | H12: =H11+H10
A13: Closing cash per Balance Sheet | B13: ='Historical BS'!B25 | C13: ='Historical BS'!C25 | D13: ='Historical BS'!D25 | E13: ='Historical BS'!E25 | F13: ='Historical BS'!F25 | G13: ='Historical BS'!G25 | H13: ='Historical BS'!H25
A15: Note: Opening cash FY20 and small acquisition/FX reconciling items (e.g. cash acquired on business combination, FX) cause minor differences vs reported closing; see AR for full reconciliation.

Sheet Historical Notes
A1: 5. HISTORICAL NOTES TO ACCOUNTS - items relevant to the model / investment thesis
A3: FY / AR | B3: Note ref. | C3: Item | D3: Reported information (summary) | E3: Model relevance | F3: Source basis | G3: Pg
A4: FY26 | B4: Note 3.2(a) | C4: PPE & useful lives | D4: SLM depreciation per Sch II; buildings 3-60y, medical equip 2-18y, plant 2-21y, computers 2-6y | E4: Basis for PPE depreciation rate (~8% of opening net block) in PPE & Depreciation schedule | F4: Annual Report FY26 / Sig. acct policies | G4: 507
A5: FY26 | B5: Note 27 | C5: Revenue from operations | D5: Rs 8,373 Cr; healthcare services (IPD/OPD), Max Lab, Max@Home, trading (pharmacy/onco drugs) | E5: Revenue build split hospital vs Max Lab vs Max@Home vs other | F5: Annual Report FY26 | G5: 501
A6: FY26 | B6: Note 4/5/6 | C6: PPE / ROU / CWIP | D6: PPE Rs 5,628 Cr, ROU Rs 1,352 Cr, CWIP Rs 592 Cr | E6: Opening balances for PPE & lease schedules | F6: Annual Report FY26 BS | G6: 500
A7: FY26 | B7: Note 21 | C7: Borrowings | D7: Gross debt Rs 2,907 Cr (NC 2,439 + current 468); term loans for expansion (Gurgaon, Mohali, Mumbai) | E7: Debt schedule opening balance; interest cost ~7% | F7: Annual Report FY26 / MD&A | G7: -
A8: FY26 | B8: Note 22 | C8: Lease liabilities (Ind AS 116) | D8: Lease liab Rs 572 Cr (NC 539 + cur 32); interest on lease Rs 54 Cr | E8: Lease schedule; lease interest 8%; ROU depreciation | F8: Annual Report FY26 | G8: -
A9: FY26 | B9: Note 16 | C9: Deferred tax | D9: Net DTL Rs 688 Cr; one-time DTA gain Rs 141 Cr on subsidiary amalgamation (FY26) | E9: Explains low FY26 ETR (13.9%); normalised ETR ~24% used in forecast | F9: Annual Report FY26 / MD&A | G9: -
A10: FY26 | B10: Note 32.01 | C10: Exceptional items | D10: Rs 48 Cr: Rs 34 Cr new labour codes + Rs 14 Cr stamp duty on merger | E10: Excluded from forecast (one-off); kept in historical as reported | F10: Annual Report FY26 | G10: 501
A11: FY26 | B11: Note 8 | C11: Goodwill | D11: Rs 3,488 Cr; indefinite life, tested for impairment (not amortised) | E11: Held flat in forecast; not depreciated | F11: Annual Report FY26 | G11: -
A12: FY26 | B12: Note 34.18 | C12: Business combinations | D12: Jaypee Healthcare (Q3FY25), Sahara/Alexis, Muthoot (Max Dwarka O&M 30y from Jun-24) | E12: Explains bed additions & goodwill step-ups FY24-FY26; Kalinga (FY27) similar | F12: Annual Report FY26 / FY25 | G12: -
A13: FY21 | B13: Note 2.1 | C13: Reverse acquisition (Ind AS 103) | D13: Radiant = accounting acquirer; FY20 = Radiant only; exceptional loss Rs 234 Cr on remeasurement | E13: FY20-21 not comparable; base year is FY26A | F13: Annual Report FY21 | G13: 226-229
A14: FY26 | B14: O&M / Silos | C14: Managed facilities (PHFs) | D14: BLK, Nanavati, Max Dwarka run under long-term O&M / service agreements; consolidated as 'Silos' | E14: 'Network' KPIs (ARPOB, beds) gross up PHFs; consolidated revenue is lower | F14: Annual Report FY26 Note 3.1 | G14: 506
A15: FY25 | B15: MD&A | C15: Payor & case mix | D15: Institutional/PSU 19.4% of rev (low margin); International 8.8%; oncology onco-drug discounting | E15: Direct-cost % and ARPOB assumptions; margin normalisation thesis | F15: Annual Report FY25 / Concall | G15: -

Sheet Historical KPIs
A1: 6. HISTORICAL OPERATING KPIs (FY20A-FY26A)
A3: Source: Annual Report MD&A operational metrics, earnings calls, CARE rating report. [B]=reported, [C]=calculated. Network/mgmt basis.
A4: INR Crore unless stated | B4: FY20A | C4: FY21A | D4: FY22A | E4: FY23A | F4: FY24A | G4: FY25A | H4: FY26A | I4: FY27E | J4: FY28E | K4: FY29E | L4: FY30E | M4: FY31E | N4: FY32E | O4: FY33E
A5: Hospital operations (network / management-reported)
A6: Operational beds (period-end) [B] | D6: 2275 | E6: 2285 | F6: 2451 | G6: 3454 | H6: 3841
A7: Occupied beds (average) [B] | D7: 1722 | E7: 1708 | F7: 1785 | G7: 2518 | H7: 2868
A8: Occupancy % [B] | D8: 0.757 | E8: 0.734 | F8: 0.728 | G8: 0.729 | H8: 0.747
A9: ARPOB (Rs 000/occ bed/day) [B] | D9: 58 | E9: 69 | F9: 75.8 | G9: 73.9 | H9: 76
A10: Average length of stay (days) [B] | D10: 4.6 | E10: 4.2 | F10: 4.1 | G10: 3.9 | H10: 4
A11: Segment revenue (Rs Cr) [B]
A12: Max Lab revenue | F12: 144 | G12: 175 | H12: 201
A13: Max@Home revenue | F13: 172 | G13: 212 | H13: 263
A14: Financial KPIs [C] (linked to Historical P&L / BS)
A15: Revenue (Rs Cr) | B15: ='Historical P&L'!B5 | C15: ='Historical P&L'!C5 | D15: ='Historical P&L'!D5 | E15: ='Historical P&L'!E5 | F15: ='Historical P&L'!F5 | G15: ='Historical P&L'!G5 | H15: ='Historical P&L'!H5
A16: Revenue growth % | C16: ='Historical P&L'!C5/'Historical P&L'!B5-1 | D16: ='Historical P&L'!D5/'Historical P&L'!C5-1 | E16: ='Historical P&L'!E5/'Historical P&L'!D5-1 | F16: ='Historical P&L'!F5/'Historical P&L'!E5-1 | G16: ='Historical P&L'!G5/'Historical P&L'!F5-1 | H16: ='Historical P&L'!H5/'Historical P&L'!G5-1
A17: EBITDA (Rs Cr) | B17: ='Historical P&L'!B28 | C17: ='Historical P&L'!C28 | D17: ='Historical P&L'!D28 | E17: ='Historical P&L'!E28 | F17: ='Historical P&L'!F28 | G17: ='Historical P&L'!G28 | H17: ='Historical P&L'!H28
A18: EBITDA margin % | B18: ='Historical P&L'!B28/'Historical P&L'!B5 | C18: ='Historical P&L'!C28/'Historical P&L'!C5 | D18: ='Historical P&L'!D28/'Historical P&L'!D5 | E18: ='Historical P&L'!E28/'Historical P&L'!E5 | F18: ='Historical P&L'!F28/'Historical P&L'!F5 | G18: ='Historical P&L'!G28/'Historical P&L'!G5 | H18: ='Historical P&L'!H28/'Historical P&L'!H5
A19: PAT margin % | B19: ='Historical P&L'!B23/'Historical P&L'!B5 | C19: ='Historical P&L'!C23/'Historical P&L'!C5 | D19: ='Historical P&L'!D23/'Historical P&L'!D5 | E19: ='Historical P&L'!E23/'Historical P&L'!E5 | F19: ='Historical P&L'!F23/'Historical P&L'!F5 | G19: ='Historical P&L'!G23/'Historical P&L'!G5 | H19: ='Historical P&L'!H23/'Historical P&L'!H5
A20: Net debt (Rs Cr) | B20: ='Historical BS'!B38+'Historical BS'!B46-'Historical BS'!B25-'Historical BS'!B26 | C20: ='Historical BS'!C38+'Historical BS'!C46-'Historical BS'!C25-'Historical BS'!C26 | D20: ='Historical BS'!D38+'Historical BS'!D46-'Historical BS'!D25-'Historical BS'!D26 | E20: ='Historical BS'!E38+'Historical BS'!E46-'Historical BS'!E25-'Historical BS'!E26 | F20: ='Historical BS'!F38+'Historical BS'!F46-'Historical BS'!F25-'Historical BS'!F26 | G20: ='Historical BS'!G38+'Historical BS'!G46-'Historical BS'!G25-'Historical BS'!G26 | H20: ='Historical BS'!H38+'Historical BS'!H46-'Historical BS'!H25-'Historical BS'!H26
A21: Net debt / EBITDA (x) | B21: =B20/'Historical P&L'!B28 | C21: =C20/'Historical P&L'!C28 | D21: =D20/'Historical P&L'!D28 | E21: =E20/'Historical P&L'!E28 | F21: =F20/'Historical P&L'!F28 | G21: =G20/'Historical P&L'!G28 | H21: =H20/'Historical P&L'!H28
A22: ROCE % (EBIT/(equity+debt)) | B22: =('Historical P&L'!B30-'Historical P&L'!B15)/('Historical BS'!B36+'Historical BS'!B38+'Historical BS'!B46) | C22: =('Historical P&L'!C30-'Historical P&L'!C15)/('Historical BS'!C36+'Historical BS'!C38+'Historical BS'!C46) | D22: =('Historical P&L'!D30-'Historical P&L'!D15)/('Historical BS'!D36+'Historical BS'!D38+'Historical BS'!D46) | E22: =('Historical P&L'!E30-'Historical P&L'!E15)/('Historical BS'!E36+'Historical BS'!E38+'Historical BS'!E46) | F22: =('Historical P&L'!F30-'Historical P&L'!F15)/('Historical BS'!F36+'Historical BS'!F38+'Historical BS'!F46) | G22: =('Historical P&L'!G30-'Historical P&L'!G15)/('Historical BS'!G36+'Historical BS'!G38+'Historical BS'!G46) | H22: =('Historical P&L'!H30-'Historical P&L'!H15)/('Historical BS'!H36+'Historical BS'!H38+'Historical BS'!H46)
A23: ROE % (PAT/equity) | B23: ='Historical P&L'!B23/'Historical BS'!B36 | C23: ='Historical P&L'!C23/'Historical BS'!C36 | D23: ='Historical P&L'!D23/'Historical BS'!D36 | E23: ='Historical P&L'!E23/'Historical BS'!E36 | F23: ='Historical P&L'!F23/'Historical BS'!F36 | G23: ='Historical P&L'!G23/'Historical BS'!G36 | H23: ='Historical P&L'!H23/'Historical BS'!H36
A24: Capex (Rs Cr) | B24: ='Historical CF'!B6*-1 | C24: ='Historical CF'!C6*-1 | D24: ='Historical CF'!D6*-1 | E24: ='Historical CF'!E6*-1 | F24: ='Historical CF'!F6*-1 | G24: ='Historical CF'!G6*-1 | H24: ='Historical CF'!H6*-1
A25: Capex / Revenue % | B25: =B24/'Historical P&L'!B5 | C25: =C24/'Historical P&L'!C5 | D25: =D24/'Historical P&L'!D5 | E25: =E24/'Historical P&L'!E5 | F25: =F24/'Historical P&L'!F5 | G25: =G24/'Historical P&L'!G5 | H25: =H24/'Historical P&L'!H5

Sheet Assumptions
A1: 7. ASSUMPTIONS & DRIVERS (Base Case)
A3: All blue cells are hardcoded inputs. Basis/Source/Justification at right (cols Q-S). Referenced by all forecast schedules.
A4: INR Crore unless stated | B4: FY20A | C4: FY21A | D4: FY22A | E4: FY23A | F4: FY24A | G4: FY25A | H4: FY26A | I4: FY27E | J4: FY28E | K4: FY29E | L4: FY30E | M4: FY31E | N4: FY32E | O4: FY33E | Q4: Basis | R4: Source | S4: Justification
A5: Operating drivers
A6: Organic bed additions (net) | I6: 609 | J6: 1200 | K6: 1100 | L6: 900 | M6: 600 | N6: 600 | O6: 600 | Q6: Disclosed expansion pipeline | R6: AR FY26 pipeline table; Q4FY26 concall | S6: Lucknow, Gurgaon Sec-56 (500), Mohali/Nanavati/Smart brownfield, Nagpur, Dwarka, Vaishali, Patparganj
A7: Acquired beds | I7: 250 | J7: 0 | K7: 0 | L7: 0 | M7: 0 | N7: 0 | O7: 0 | Q7: Announced M&A | R7: Q4FY26 concall | S7: Kalinga Hospital, Bhubaneswar (250 beds) completed FY27
A8: Blended occupancy % (avg beds) | I8: 0.735 | J8: 0.725 | K8: 0.73 | L8: 0.74 | M8: 0.745 | N8: 0.75 | O8: 0.75 | Q8: Historical 73-75% + ramp | R8: AR MD&A; CARE report | S8: Dips as new towers commission then recovers to ~75%; mgmt: beds opened only with occupancy visibility
A9: ARPOB growth % YoY | I9: 0.06 | J9: 0.06 | K9: 0.065 | L9: 0.07 | M9: 0.07 | N9: 0.07 | O9: 0.07 | Q9: Hist matured ARPOB +7% (CARE) | R9: CARE report; concall | S9: Price revisions, case-mix, international, oncology bunkers; net of new-bed dilution
A10: Max Lab revenue growth % | I10: 0.15 | J10: 0.15 | K10: 0.14 | L10: 0.14 | M10: 0.13 | N10: 0.13 | O10: 0.12 | Q10: Hist +15-24% | R10: AR FY26 (Rs201Cr, +15%) | S10: Diagnostics expansion to 60+ cities; moderating growth
A11: Max@Home revenue growth % | I11: 0.22 | J11: 0.2 | K11: 0.18 | L11: 0.17 | M11: 0.16 | N11: 0.15 | O11: 0.15 | Q11: Hist +24% | R11: AR FY26 (Rs263Cr, +24%) | S11: Home healthcare scale-up; moderating
A12: Other operating revenue (Rs Cr) | I12: 50 | J12: 55 | K12: 60 | L12: 66 | M12: 72 | N12: 79 | O12: 87 | Q12: Small residual | R12: Analyst estimate | S12: Ancillary/other operating income
A13: Other income % of revenue | I13: 0.018 | J13: 0.018 | K13: 0.018 | L13: 0.018 | M13: 0.018 | N13: 0.018 | O13: 0.018 | Q13: Hist ~1.9% | R13: AR FY26 | S13: Finance income on loans to PHFs / deposits
A14: Cost ratios (% of revenue)
A15: Direct cost (drugs/consumables) % | I15: 0.215 | J15: 0.214 | K15: 0.213 | L15: 0.212 | M15: 0.211 | N15: 0.21 | O15: 0.21 | Q15: Hist 20.7-21.4% | R15: AR MD&A | S15: Case mix / onco pass-through; eases as mix normalises
A16: Employee cost % | I16: 0.163 | J16: 0.16 | K16: 0.158 | L16: 0.156 | M16: 0.155 | N16: 0.154 | O16: 0.153 | Q16: Hist 16.2% | R16: AR FY26 MD&A | S16: Operating leverage as revenue scales
A17: Professional & consultancy (doctor) fee % | I17: 0.215 | J17: 0.214 | K17: 0.213 | L17: 0.212 | M17: 0.211 | N17: 0.21 | O17: 0.21 | Q17: Hist 21.4% | R17: AR FY26 MD&A | S17: Variable clinician payout; broadly stable
A18: Other operating expenses % | I18: 0.142 | J18: 0.14 | K18: 0.138 | L18: 0.136 | M18: 0.135 | N18: 0.134 | O18: 0.133 | Q18: Hist 14.2% | R18: AR FY26 MD&A | S18: Operating leverage / cost discipline
A19: Capex, PPE & leases
A20: Total capex (Rs Cr) | I20: 2000 | J20: 2500 | K20: 2100 | L20: 1500 | M20: 1300 | N20: 1350 | O20: 1400 | Q20: Pipeline capex to FY30 ~Rs6,672 Cr + routine + land | R20: AR FY26; concall | S20: Growth capex peaks FY28; + maintenance ~4% of revenue
A21: (growth capex ex land/routine per AR) | I21: 1637 | J21: 2280 | K21: 1770 | L21: 985 | M21: 0 | N21: 0 | O21: 0 | Q21: AR pipeline outflow | R21: AR FY26 pipeline table | S21: Memo only; not linked
A22: PPE depreciation rate (% opening net) | I22: 0.08 | J22: 0.08 | K22: 0.08 | L22: 0.08 | M22: 0.08 | N22: 0.08 | O22: 0.08 | Q22: Hist ~8% | R22: AR useful lives (Sch II) | S22: Blended block; buildings long-life, equipment 2-18y
A23: ROU depreciation / lease additions (Rs Cr) | I23: 60 | J23: 60 | K23: 60 | L23: 60 | M23: 60 | N23: 60 | O23: 60 | Q23: Steady state | R23: AR FY26 | S23: Leases modelled at steady state (additions=payments=dep)
A24: Intangible amortisation (Rs Cr, flat) | I24: 55 | J24: 55 | K24: 55 | L24: 55 | M24: 55 | N24: 55 | O24: 55 | Q24: Hist ~Rs50 Cr | R24: AR FY26 Note 9 | S24: Finite-life service agreements; goodwill/trademark not amortised
A25: Lease interest rate % | I25: 0.08 | J25: 0.08 | K25: 0.08 | L25: 0.08 | M25: 0.08 | N25: 0.08 | O25: 0.08 | Q25: Ind AS 116 IBR | R25: AR FY26 Note 22 | S25: Incremental borrowing rate on lease liabilities
A26: Working capital (% of revenue)
A27: Trade receivables % of revenue | I27: 0.116 | J27: 0.116 | K27: 0.116 | L27: 0.116 | M27: 0.116 | N27: 0.116 | O27: 0.116 | Q27: Hist ~11.6% (~42 DSO) | R27: AR BS | S27: Rising institutional/insurance receivables
A28: Inventories % of revenue | I28: 0.0137 | J28: 0.0137 | K28: 0.0137 | L28: 0.0137 | M28: 0.0137 | N28: 0.0137 | O28: 0.0137 | Q28: Hist ~1.4% | R28: AR BS | S28: Drugs/consumables stock
A29: Trade payables % of revenue | I29: 0.1026 | J29: 0.1026 | K29: 0.1026 | L29: 0.1026 | M29: 0.1026 | N29: 0.1026 | O29: 0.1026 | Q29: Hist ~10.3% | R29: AR BS | S29: Supplier + capital creditors
A30: Other current assets % of revenue | I30: 0.0065 | J30: 0.0065 | K30: 0.0065 | L30: 0.0065 | M30: 0.0065 | N30: 0.0065 | O30: 0.0065 | Q30: Hist ~0.65% | R30: AR BS
A31: Other current liabilities % of revenue | I31: 0.0207 | J31: 0.0207 | K31: 0.0207 | L31: 0.0207 | M31: 0.0207 | N31: 0.0207 | O31: 0.0207 | Q31: Hist ~2.1% | R31: AR BS | S31: Deferred income / statutory dues
A32: Financing & tax
A33: Gross debt (period-end, Rs Cr) | I33: 3400 | J33: 3900 | K33: 3900 | L33: 3400 | M33: 2800 | N33: 2200 | O33: 1600 | Q33: Fund capex; delever on FCF | R33: CARE (net lev<1.5x); concall | S33: Rises through FY28-29 capex peak, then delevers; net debt/EBITDA <1.5x
A34: Borrowing interest rate % | I34: 0.07 | J34: 0.07 | K34: 0.07 | L34: 0.07 | M34: 0.07 | N34: 0.07 | O34: 0.07 | Q34: Hist ~6-7% | R34: AR FY26; CARE AA+ | S34: AA+ rated cost of funds
A35: Effective tax rate % | I35: 0.24 | J35: 0.24 | K35: 0.24 | L35: 0.24 | M35: 0.24 | N35: 0.24 | O35: 0.24 | Q35: Hist normalised ~23-24% | R35: AR FY24-25 | S35: FY26 ETR distorted by one-time DTA gain; normalised 24%
A36: Dividend payout % of PAT | I36: 0.12 | J36: 0.12 | K36: 0.12 | L36: 0.12 | M36: 0.12 | N36: 0.12 | O36: 0.12 | Q36: Hist ~10% | R36: AR FY26 | S36: Retain for growth capex
A37: Valuation inputs
A38: Risk-free rate (India 10Y G-sec) | I38: 0.069 | R38: tradingeconomics.com Jul-2026 | S38: 10Y G-sec ~6.82%
A39: Equity risk premium | I39: 0.07 | R39: Damodaran India ERP | S39: ~7.0%
A40: Beta (levered) | I40: 0.75 | R40: Sector beta | S40: Defensive healthcare; ~0.75
A41: Pre-tax cost of debt | I41: 0.07 | R41: AR / CARE AA+ | S41: ~7.0%
A42: Terminal growth rate | I42: 0.055 | R42: Analyst judgement | S42: Below nominal GDP; conservative
A43: Current market price (Rs) | I43: 1080.4 | R43: NSE 24-Jul-2026 | S43: MAXHEALTH
A44: Shares outstanding (Cr) | I44: 97.31 | R44: AR FY26 | S44: 97.31 Cr shares (Rs10 FV)
A45: Net debt FY26 (Rs Cr) | I45: 2206.22 | R45: AR FY26 BS / MD&A | S45: Gross debt - cash & bank
A46: Target EV/EBITDA (x) | I46: 30 | R46: Peer set | S46: Premium to peers (quality/growth)
A47: Target P/E (x) | I47: 52 | R47: Peer set | S47: Forward multiple
A48: DCF exit EV/EBITDA (x) | I48: 22 | R48: Analyst | S48: Terminal exit multiple alt.

Sheet Bed Capacity
A1: 9. BED CAPACITY SCHEDULE
A4: INR Crore unless stated | B4: FY20A | C4: FY21A | D4: FY22A | E4: FY23A | F4: FY24A | G4: FY25A | H4: FY26A | I4: FY27E | J4: FY28E | K4: FY29E | L4: FY30E | M4: FY31E | N4: FY32E | O4: FY33E
A5: Opening operational beds | I5: ='Historical KPIs'!H6 | J5: =I9 | K5: =J9 | L5: =K9 | M5: =L9 | N5: =M9 | O5: =N9
A6: Add: organic bed additions | I6: ='Assumptions'!I6 | J6: ='Assumptions'!J6 | K6: ='Assumptions'!K6 | L6: ='Assumptions'!L6 | M6: ='Assumptions'!M6 | N6: ='Assumptions'!N6 | O6: ='Assumptions'!O6
A7: Add: acquired beds | I7: ='Assumptions'!I7 | J7: ='Assumptions'!J7 | K7: ='Assumptions'!K7 | L7: ='Assumptions'!L7 | M7: ='Assumptions'!M7 | N7: ='Assumptions'!N7 | O7: ='Assumptions'!O7
A8: Less: decommissioned beds | I8: 0 | J8: 0 | K8: 0 | L8: 0 | M8: 0 | N8: 0 | O8: 0
A9: Closing operational beds | I9: =I5+I6+I7-I8 | J9: =J5+J6+J7-J8 | K9: =K5+K6+K7-K8 | L9: =L5+L6+L7-L8 | M9: =M5+M6+M7-M8 | N9: =N5+N6+N7-N8 | O9: =O5+O6+O7-O8
A10: Average operational beds | I10: =(I5+I9)/2 | J10: =(J5+J9)/2 | K10: =(K5+K9)/2 | L10: =(L5+L9)/2 | M10: =(M5+M9)/2 | N10: =(N5+N9)/2 | O10: =(O5+O9)/2
A12: Opening FY27 = FY26A operational beds (3,841). Pipeline: Lucknow, Gurgaon Sec-56 (500), Mohali/Nanavati/Smart brownfield, Nagpur (100), Dwarka (260), Vaishali (200), Patparganj (400) + Kalinga acq (250).

Sheet Occupancy ARPOB
A1: 10. OCCUPANCY & ARPOB SCHEDULE
A4: INR Crore unless stated | B4: FY20A | C4: FY21A | D4: FY22A | E4: FY23A | F4: FY24A | G4: FY25A | H4: FY26A | I4: FY27E | J4: FY28E | K4: FY29E | L4: FY30E | M4: FY31E | N4: FY32E | O4: FY33E
A5: Average operational beds | I5: ='Bed Capacity'!I10 | J5: ='Bed Capacity'!J10 | K5: ='Bed Capacity'!K10 | L5: ='Bed Capacity'!L10 | M5: ='Bed Capacity'!M10 | N5: ='Bed Capacity'!N10 | O5: ='Bed Capacity'!O10
A6: Occupancy % | I6: ='Assumptions'!I8 | J6: ='Assumptions'!J8 | K6: ='Assumptions'!K8 | L6: ='Assumptions'!L8 | M6: ='Assumptions'!M8 | N6: ='Assumptions'!N8 | O6: ='Assumptions'!O8
A7: Occupied beds (avg) | I7: =I5*I6 | J7: =J5*J6 | K7: =K5*K6 | L7: =L5*L6 | M7: =M5*M6 | N7: =N5*N6 | O7: =O5*O6
A8: ARPOB (Rs 000/occ bed/day) | I8: ='Historical KPIs'!H9*(1+'Assumptions'!I9) | J8: =I8*(1+'Assumptions'!J9) | K8: =J8*(1+'Assumptions'!K9) | L8: =K8*(1+'Assumptions'!L9) | M8: =L8*(1+'Assumptions'!M9) | N8: =M8*(1+'Assumptions'!N9) | O8: =N8*(1+'Assumptions'!O9)
A9: ARPOB growth % | I9: ='Assumptions'!I9 | J9: ='Assumptions'!J9 | K9: ='Assumptions'!K9 | L9: ='Assumptions'!L9 | M9: ='Assumptions'!M9 | N9: ='Assumptions'!N9 | O9: ='Assumptions'!O9

Sheet Revenue Build
A1: 11. REVENUE BUILD
A4: INR Crore unless stated | B4: FY20A | C4: FY21A | D4: FY22A | E4: FY23A | F4: FY24A | G4: FY25A | H4: FY26A | I4: FY27E | J4: FY28E | K4: FY29E | L4: FY30E | M4: FY31E | N4: FY32E | O4: FY33E
A5: Occupied beds (avg) | I5: ='Occupancy ARPOB'!I7 | J5: ='Occupancy ARPOB'!J7 | K5: ='Occupancy ARPOB'!K7 | L5: ='Occupancy ARPOB'!L7 | M5: ='Occupancy ARPOB'!M7 | N5: ='Occupancy ARPOB'!N7 | O5: ='Occupancy ARPOB'!O7
A6: ARPOB (Rs 000/day) | I6: ='Occupancy ARPOB'!I8 | J6: ='Occupancy ARPOB'!J8 | K6: ='Occupancy ARPOB'!K8 | L6: ='Occupancy ARPOB'!L8 | M6: ='Occupancy ARPOB'!M8 | N6: ='Occupancy ARPOB'!N8 | O6: ='Occupancy ARPOB'!O8
A7: Operating days | I7: 365 | J7: 365 | K7: 365 | L7: 365 | M7: 365 | N7: 365 | O7: 365
A8: Hospital revenue (Rs Cr) = beds x ARPOB x 365 | I8: =I5*I6*1000*365/10000000 | J8: =J5*J6*1000*365/10000000 | K8: =K5*K6*1000*365/10000000 | L8: =L5*L6*1000*365/10000000 | M8: =M5*M6*1000*365/10000000 | N8: =N5*N6*1000*365/10000000 | O8: =O5*O6*1000*365/10000000
A9: Max Lab revenue | I9: ='Historical KPIs'!H12*(1+'Assumptions'!I10) | J9: =I9*(1+'Assumptions'!J10) | K9: =J9*(1+'Assumptions'!K10) | L9: =K9*(1+'Assumptions'!L10) | M9: =L9*(1+'Assumptions'!M10) | N9: =M9*(1+'Assumptions'!N10) | O9: =N9*(1+'Assumptions'!O10)
A10: Max@Home revenue | I10: ='Historical KPIs'!H13*(1+'Assumptions'!I11) | J10: =I10*(1+'Assumptions'!J11) | K10: =J10*(1+'Assumptions'!K11) | L10: =K10*(1+'Assumptions'!L11) | M10: =L10*(1+'Assumptions'!M11) | N10: =M10*(1+'Assumptions'!N11) | O10: =N10*(1+'Assumptions'!O11)
A11: Other operating revenue | I11: ='Assumptions'!I12 | J11: ='Assumptions'!J12 | K11: ='Assumptions'!K12 | L11: ='Assumptions'!L12 | M11: ='Assumptions'!M12 | N11: ='Assumptions'!N12 | O11: ='Assumptions'!O12
A12: Total revenue from operations | I12: =I8+I9+I10+I11 | J12: =J8+J9+J10+J11 | K12: =K8+K9+K10+K11 | L12: =L8+L9+L10+L11 | M12: =M8+M9+M10+M11 | N12: =N8+N9+N10+N11 | O12: =O8+O9+O10+O11
A13: Revenue growth % | I13: =I12/'Historical P&L'!H5-1 | J13: =J12/I12-1 | K13: =K12/J12-1 | L13: =L12/K12-1 | M13: =M12/L12-1 | N13: =N12/M12-1 | O13: =O12/N12-1
A14: Calibration check vs FY26A reported:
A15: FY26 build hospital rev (memo) | H15: ='Historical KPIs'!H7*'Historical KPIs'!H9*1000*365/10000000
A16: FY26 build hospital revenue ~Rs7,956 Cr vs reported total Rs8,373 Cr less Max Lab (201) & Max@Home (263) = ~Rs7,909 Cr hospital+pharmacy; +0.6% variance (grossing/eliminations). Consolidated statutory revenue used in Integrated Model.

Sheet Direct Cost GP
A1: 12. DIRECT COST & ANALYTICAL GROSS PROFIT BUILD
A3: Methodology: Analytical Gross Profit = Revenue - Direct operating cost (drugs, consumables & implants, net of inventory change). Company does not report a conventional gross profit line.
A4: INR Crore unless stated | B4: FY20A | C4: FY21A | D4: FY22A | E4: FY23A | F4: FY24A | G4: FY25A | H4: FY26A | I4: FY27E | J4: FY28E | K4: FY29E | L4: FY30E | M4: FY31E | N4: FY32E | O4: FY33E
A5: Revenue from operations | B5: ='Historical P&L'!B5 | C5: ='Historical P&L'!C5 | D5: ='Historical P&L'!D5 | E5: ='Historical P&L'!E5 | F5: ='Historical P&L'!F5 | G5: ='Historical P&L'!G5 | H5: ='Historical P&L'!H5 | I5: ='Revenue Build'!I12 | J5: ='Revenue Build'!J12 | K5: ='Revenue Build'!K12 | L5: ='Revenue Build'!L12 | M5: ='Revenue Build'!M12 | N5: ='Revenue Build'!N12 | O5: ='Revenue Build'!O12
A6: Direct cost % of revenue | B6: ='Historical P&L'!B25/'Historical P&L'!B5 | C6: ='Historical P&L'!C25/'Historical P&L'!C5 | D6: ='Historical P&L'!D25/'Historical P&L'!D5 | E6: ='Historical P&L'!E25/'Historical P&L'!E5 | F6: ='Historical P&L'!F25/'Historical P&L'!F5 | G6: ='Historical P&L'!G25/'Historical P&L'!G5 | H6: ='Historical P&L'!H25/'Historical P&L'!H5 | I6: ='Assumptions'!I15 | J6: ='Assumptions'!J15 | K6: ='Assumptions'!K15 | L6: ='Assumptions'!L15 | M6: ='Assumptions'!M15 | N6: ='Assumptions'!N15 | O6: ='Assumptions'!O15
A7: Direct cost (drugs/consumables, net) | B7: ='Historical P&L'!B25 | C7: ='Historical P&L'!C25 | D7: ='Historical P&L'!D25 | E7: ='Historical P&L'!E25 | F7: ='Historical P&L'!F25 | G7: ='Historical P&L'!G25 | H7: ='Historical P&L'!H25 | I7: =I5*I6 | J7: =J5*J6 | K7: =K5*K6 | L7: =L5*L6 | M7: =M5*M6 | N7: =N5*N6 | O7: =O5*O6
A8: Analytical Gross Profit | B8: =B5-B7 | C8: =C5-C7 | D8: =D5-D7 | E8: =E5-E7 | F8: =F5-F7 | G8: =G5-G7 | H8: =H5-H7 | I8: =I5-I7 | ... O8: =O5-O7
A9: Analytical Gross Margin % | B9: =B8/B5 | C9: =C8/C5 | D9: =D8/D5 | E9: =E8/E5 | F9: =F8/F5 | G9: =G8/G5 | H9: =H8/H5 | I9: =I8/I5 | ... O9: =O8/O5

Sheet Opex Build
A1: 13. OPERATING EXPENSE BUILD
A4: INR Crore unless stated | B4: FY20A | C4: FY21A | D4: FY22A | E4: FY23A | F4: FY24A | G4: FY25A | H4: FY26A | I4: FY27E | J4: FY28E | K4: FY29E | L4: FY30E | M4: FY31E | N4: FY32E | O4: FY33E
A5: Revenue from operations | B5: ='Historical P&L'!B5 | C5: ='Historical P&L'!C5 | D5: ='Historical P&L'!D5 | E5: ='Historical P&L'!E5 | F5: ='Historical P&L'!F5 | G5: ='Historical P&L'!G5 | H5: ='Historical P&L'!H5 | I5: ='Revenue Build'!I12 | J5: ='Revenue Build'!J12 | K5: ='Revenue Build'!K12 | L5: ='Revenue Build'!L12 | M5: ='Revenue Build'!M12 | N5: ='Revenue Build'!N12 | O5: ='Revenue Build'!O12
A6: Employee benefits expense % of revenue | B6: ='Historical P&L'!B11/'Historical P&L'!B5 | C6: ='Historical P&L'!C11/'Historical P&L'!C5 | D6: ='Historical P&L'!D11/'Historical P&L'!D5 | E6: ='Historical P&L'!E11/'Historical P&L'!E5 | F6: ='Historical P&L'!F11/'Historical P&L'!F5 | G6: ='Historical P&L'!G11/'Historical P&L'!G5 | H6: ='Historical P&L'!H11/'Historical P&L'!H5 | I6: ='Assumptions'!I16 | J6: ='Assumptions'!J16 | K6: ='Assumptions'!K16 | L6: ='Assumptions'!L16 | M6: ='Assumptions'!M16 | N6: ='Assumptions'!N16 | O6: ='Assumptions'!O16
A7: Employee benefits expense | B7: ='Historical P&L'!B11 | C7: ='Historical P&L'!C11 | D7: ='Historical P&L'!D11 | E7: ='Historical P&L'!E11 | F7: ='Historical P&L'!F11 | G7: ='Historical P&L'!G11 | H7: ='Historical P&L'!H11 | I7: =I5*I6 | J7: =J5*J6 | K7: =K5*K6 | L7: =L5*L6 | M7: =M5*M6 | N7: =N5*N6 | O7: =O5*O6
A8: Professional & consultancy fee % of revenue | B8: ='Historical P&L'!B12/'Historical P&L'!B5 | C8: ='Historical P&L'!C12/'Historical P&L'!C5 | D8: ='Historical P&L'!D12/'Historical P&L'!D5 | E8: ='Historical P&L'!E12/'Historical P&L'!E5 | F8: ='Historical P&L'!F12/'Historical P&L'!F5 | G8: ='Historical P&L'!G12/'Historical P&L'!G5 | H8: ='Historical P&L'!H12/'Historical P&L'!H5 | I8: ='Assumptions'!I17 | J8: ='Assumptions'!J17 | K8: ='Assumptions'!K17 | L8: ='Assumptions'!L17 | M8: ='Assumptions'!M17 | N8: ='Assumptions'!N17 | O8: ='Assumptions'!O17
A9: Professional & consultancy fee | B9: ='Historical P&L'!B12 | C9: ='Historical P&L'!C12 | D9: ='Historical P&L'!D12 | E9: ='Historical P&L'!E12 | F9: ='Historical P&L'!F12 | G9: ='Historical P&L'!G12 | H9: ='Historical P&L'!H12 | I9: =I5*I8 | J9: =J5*J8 | K9: =K5*K8 | L9: =L5*L8 | M9: =M5*M8 | N9: =N5*N8 | O9: =O5*O8
A10: Other operating expenses % of revenue | B10: ='Historical P&L'!B13/'Historical P&L'!B5 | C10: ='Historical P&L'!C13/'Historical P&L'!C5 | D10: ='Historical P&L'!D13/'Historical P&L'!D5 | E10: ='Historical P&L'!E13/'Historical P&L'!E5 | F10: ='Historical P&L'!F13/'Historical P&L'!F5 | G10: ='Historical P&L'!G13/'Historical P&L'!G5 | H10: ='Historical P&L'!H13/'Historical P&L'!H5 | I10: ='Assumptions'!I18 | J10: ='Assumptions'!J18 | K10: ='Assumptions'!K18 | L10: ='Assumptions'!L18 | M10: ='Assumptions'!M18 | N10: ='Assumptions'!N18 | O10: ='Assumptions'!O18
A11: Other operating expenses | B11: ='Historical P&L'!B13 | C11: ='Historical P&L'!C13 | D11: ='Historical P&L'!D13 | E11: ='Historical P&L'!E13 | F11: ='Historical P&L'!F13 | G11: ='Historical P&L'!G13 | H11: ='Historical P&L'!H13 | I11: =I5*I10 | J11: =J5*J10 | K11: =K5*K10 | L11: =L5*L10 | M11: =M5*M10 | N11: =N5*N10 | O11: =O5*O10
A12: Total operating expenses (excl. direct) | B12: =B7+B9+B11 | C12: =C7+C9+C11 | D12: =D7+D9+D11 | E12: =E7+E9+E11 | F12: =F7+F9+F11 | G12: =G7+G9+G11 | H12: =H7+H9+H11 | I12: =I7+I9+I11 | ... O12: =O7+O9+O11

Sheet EBITDA Build
A1: 14. EBITDA BRIDGE
A4: INR Crore unless stated | B4: FY20A | C4: FY21A | D4: FY22A | E4: FY23A | F4: FY24A | G4: FY25A | H4: FY26A | I4: FY27E | J4: FY28E | K4: FY29E | L4: FY30E | M4: FY31E | N4: FY32E | O4: FY33E
A5: Revenue from operations | B5: ='Historical P&L'!B5 | C5: ='Historical P&L'!C5 | D5: ='Historical P&L'!D5 | E5: ='Historical P&L'!E5 | F5: ='Historical P&L'!F5 | G5: ='Historical P&L'!G5 | H5: ='Historical P&L'!H5 | I5: ='Revenue Build'!I12 | J5: ='Revenue Build'!J12 | K5: ='Revenue Build'!K12 | L5: ='Revenue Build'!L12 | M5: ='Revenue Build'!M12 | N5: ='Revenue Build'!N12 | O5: ='Revenue Build'!O12
A6: Less: Direct cost | B6: =-'Direct Cost GP'!B7 | C6: =-'Direct Cost GP'!C7 | D6: =-'Direct Cost GP'!D7 | E6: =-'Direct Cost GP'!E7 | F6: =-'Direct Cost GP'!F7 | G6: =-'Direct Cost GP'!G7 | H6: =-'Direct Cost GP'!H7 | I6: =-'Direct Cost GP'!I7 | ... O6: =-'Direct Cost GP'!O7
A7: Analytical Gross Profit | B7: ='Direct Cost GP'!B8 | C7: ='Direct Cost GP'!C8 | D7: ='Direct Cost GP'!D8 | E7: ='Direct Cost GP'!E8 | F7: ='Direct Cost GP'!F8 | G7: ='Direct Cost GP'!G8 | H7: ='Direct Cost GP'!H8 | I7: ='Direct Cost GP'!I8 | ... O7: ='Direct Cost GP'!O8
A8: Less: Employee cost | B8: =-'Opex Build'!B7 | C8: =-'Opex Build'!C7 | D8: =-'Opex Build'!D7 | E8: =-'Opex Build'!E7 | F8: =-'Opex Build'!F7 | G8: =-'Opex Build'!G7 | H8: =-'Opex Build'!H7 | I8: =-'Opex Build'!I7 | ... O8: =-'Opex Build'!O7
A9: Less: Professional & consultancy fee | B9: =-'Opex Build'!B9 | C9: =-'Opex Build'!C9 | D9: =-'Opex Build'!D9 | E9: =-'Opex Build'!E9 | F9: =-'Opex Build'!F9 | G9: =-'Opex Build'!G9 | H9: =-'Opex Build'!H9 | I9: =-'Opex Build'!I9 | ... O9: =-'Opex Build'!O9
A10: Less: Other operating expenses | B10: =-'Opex Build'!B11 | C10: =-'Opex Build'!C11 | D10: =-'Opex Build'!D11 | E10: =-'Opex Build'!E11 | F10: =-'Opex Build'!F11 | G10: =-'Opex Build'!G11 | H10: =-'Opex Build'!H11 | I10: =-'Opex Build'!I11 | ... O10: =-'Opex Build'!O11
A11: EBITDA (excl. other income) | B11: =B7+B8+B9+B10 | C11: =C7+C8+C9+C10 | D11: =D7+D8+D9+D10 | E11: =E7+E8+E9+E10 | F11: =F7+F8+F9+F10 | G11: =G7+G8+G9+G10 | H11: =H7+H8+H9+H10 | I11: =I7+I8+I9+I10 | ... O11: =O7+O8+O9+O10
A12: EBITDA margin % | B12: =B11/B5 | C12: =C11/C5 | D12: =D11/D5 | E12: =E11/E5 | F12: =F11/F5 | G12: =G11/G5 | H12: =H11/H5 | I12: =I11/I5 | ... O12: =O11/O5
A13: Add: Other income | B13: ='Historical P&L'!B6 | C13: ='Historical P&L'!C6 | D13: ='Historical P&L'!D6 | E13: ='Historical P&L'!E6 | F13: ='Historical P&L'!F6 | G13: ='Historical P&L'!G6 | H13: ='Historical P&L'!H6 | I13: ='Revenue Build'!I12*'Assumptions'!I13 | J13: ='Revenue Build'!J12*'Assumptions'!J13 | K13: ='Revenue Build'!K12*'Assumptions'!K13 | L13: ='Revenue Build'!L12*'Assumptions'!L13 | M13: ='Revenue Build'!M12*'Assumptions'!M13 | N13: ='Revenue Build'!N12*'Assumptions'!N13 | O13: ='Revenue Build'!O12*'Assumptions'!O13
A14: PBIDT (EBITDA + other income) | B14: =B11+B13 | C14: =C11+C13 | D14: =D11+D13 | E14: =E11+E13 | F14: =F11+F13 | G14: =G11+G13 | H14: =H11+H13 | I14: =I11+I13 | ... O14: =O11+O13

Sheet Capex Expansion
A1: 15. CAPEX & EXPANSION SCHEDULE
A4: INR Crore unless stated | B4: FY20A | C4: FY21A | D4: FY22A | E4: FY23A | F4: FY24A | G4: FY25A | H4: FY26A | I4: FY27E | J4: FY28E | K4: FY29E | L4: FY30E | M4: FY31E | N4: FY32E | O4: FY33E
A5: Total capex (Rs Cr) | B5: ='Historical CF'!B6*-1 | C5: ='Historical CF'!C6*-1 | D5: ='Historical CF'!D6*-1 | E5: ='Historical CF'!E6*-1 | F5: ='Historical CF'!F6*-1 | G5: ='Historical CF'!G6*-1 | H5: ='Historical CF'!H6*-1 | I5: ='Assumptions'!I20 | J5: ='Assumptions'!J20 | K5: ='Assumptions'!K20 | L5: ='Assumptions'!L20 | M5: ='Assumptions'!M20 | N5: ='Assumptions'!N20 | O5: ='Assumptions'!O20
A6: Revenue | B6: ='Historical P&L'!B5 | C6: ='Historical P&L'!C5 | D6: ='Historical P&L'!D5 | E6: ='Historical P&L'!E5 | F6: ='Historical P&L'!F5 | G6: ='Historical P&L'!G5 | H6: ='Historical P&L'!H5 | I6: ='Revenue Build'!I12 | J6: ='Revenue Build'!J12 | K6: ='Revenue Build'!K12 | L6: ='Revenue Build'!L12 | M6: ='Revenue Build'!M12 | N6: ='Revenue Build'!N12 | O6: ='Revenue Build'!O12
A7: Capex / Revenue % | B7: =B5/B6 | C7: =C5/C6 | D7: =D5/D6 | E7: =E5/E6 | F7: =F5/F6 | G7: =G5/G6 | H7: =H5/H6 | I7: =I5/I6 | ... O7: =O5/O6
A8: Beds added (organic+acq) | I8: ='Bed Capacity'!I6+'Bed Capacity'!I7 | J8: ='Bed Capacity'!J6+'Bed Capacity'!J7 | K8: ='Bed Capacity'!K6+'Bed Capacity'!K7 | L8: ='Bed Capacity'!L6+'Bed Capacity'!L7 | M8: ='Bed Capacity'!M6+'Bed Capacity'!M7 | N8: ='Bed Capacity'!N6+'Bed Capacity'!N7 | O8: ='Bed Capacity'!O6+'Bed Capacity'!O7
A9: Capex per bed added (Rs Cr) | I9: =I5/I8 | J9: =J5/J8 | K9: =K5/K8 | L9: =L5/L8 | M9: =M5/M8 | N9: =N5/N8 | O9: =O5/O8
A11: Pipeline (AR FY26 / Q4FY26 concall): growth capex FY27 Rs1,637 Cr, FY28 Rs2,280 Cr, FY29 Rs1,770 Cr, FY30 Rs985 Cr (ex land & routine). Model adds ~4% maintenance capex + land.

Sheet PPE Depreciation
A1: 16. PPE & DEPRECIATION SCHEDULE
A4: INR Crore unless stated | B4: FY20A | C4: FY21A | D4: FY22A | E4: FY23A | F4: FY24A | G4: FY25A | H4: FY26A | I4: FY27E | J4: FY28E | K4: FY29E | L4: FY30E | M4: FY31E | N4: FY32E | O4: FY33E
A5: Property, plant & equipment (net)
A6: Opening net PPE | I6: ='Historical BS'!H6 | J6: =I9 | K6: =J9 | L6: =K9 | M6: =L9 | N6: =M9 | O6: =N9
A7: Add: Capex | I7: ='Capex Expansion'!I5 | J7: ='Capex Expansion'!J5 | K7: ='Capex Expansion'!K5 | L7: ='Capex Expansion'!L5 | M7: ='Capex Expansion'!M5 | N7: ='Capex Expansion'!N5 | O7: ='Capex Expansion'!O5
A8: Less: PPE depreciation (rate x opening) | I8: =I6*'Assumptions'!I22 | J8: =J6*'Assumptions'!I22 | K8: =K6*'Assumptions'!I22 | L8: =L6*'Assumptions'!I22 | M8: =M6*'Assumptions'!I22 | N8: =N6*'Assumptions'!I22 | O8: =O6*'Assumptions'!I22
A9: Closing net PPE | I9: =I6+I7-I8 | J9: =J6+J7-J8 | K9: =K6+K7-K8 | L9: =L6+L7-L8 | M9: =M6+M7-M8 | N9: =N6+N7-N8 | O9: =O6+O7-O8
A10: Right-of-use assets & intangibles
A11: Opening ROU assets | I11: ='Historical BS'!H7 | J11: =I14 | K11: =J14 | L11: =K14 | M11: =L14 | N11: =M14 | O11: =N14
A12: Add: lease additions | I12: ='Assumptions'!I23 | J12: ='Assumptions'!I23 | K12: ='Assumptions'!I23 | L12: ='Assumptions'!I23 | M12: ='Assumptions'!I23 | N12: ='Assumptions'!I23 | O12: ='Assumptions'!I23
A13: Less: ROU depreciation | I13: ='Assumptions'!I23 | J13: ='Assumptions'!I23 | K13: ='Assumptions'!I23 | L13: ='Assumptions'!I23 | M13: ='Assumptions'!I23 | N13: ='Assumptions'!I23 | O13: ='Assumptions'!I23
A14: Closing ROU assets | I14: =I11+I12-I13 | J14: =J11+J12-J13 | K14: =K11+K12-K13 | L14: =L11+L12-L13 | M14: =M11+M12-M13 | N14: =N11+N12-N13 | O14: =O11+O12-O13
A15: Opening intangibles (finite+indef.) | I15: ='Historical BS'!H11 | J15: =I17 | K15: =J17 | L15: =K17 | M15: =L17 | N15: =M17 | O15: =N17
A16: Less: intangible amortisation | I16: ='Assumptions'!I24 | J16: ='Assumptions'!I24 | K16: ='Assumptions'!I24 | L16: ='Assumptions'!I24 | M16: ='Assumptions'!I24 | N16: ='Assumptions'!I24 | O16: ='Assumptions'!I24
A17: Closing intangibles | I17: =I15-I16 | J17: =J15-J16 | K17: =K15-K16 | L17: =L15-L16 | M17: =M15-M16 | N17: =N15-N16 | O17: =O15-O16
A18: Total Depreciation & amortisation | I18: =I8+I13+I16 | J18: =J8+J13+J16 | K18: =K8+K13+K16 | L18: =L8+L13+L16 | M18: =M8+M13+M16 | N18: =N8+N13+N16 | O18: =O8+O13+O16

Sheet Working Capital
A1: 17. WORKING CAPITAL SCHEDULE
A4: INR Crore unless stated | B4: FY20A | C4: FY21A | D4: FY22A | E4: FY23A | F4: FY24A | G4: FY25A | H4: FY26A | I4: FY27E | J4: FY28E | K4: FY29E | L4: FY30E | M4: FY31E | N4: FY32E | O4: FY33E
A5: Revenue | B5: ='Historical P&L'!B5 | C5: ='Historical P&L'!C5 | D5: ='Historical P&L'!D5 | E5: ='Historical P&L'!E5 | F5: ='Historical P&L'!F5 | G5: ='Historical P&L'!G5 | H5: ='Historical P&L'!H5 | I5: ='Revenue Build'!I12 | J5: ='Revenue Build'!J12 | K5: ='Revenue Build'!K12 | L5: ='Revenue Build'!L12 | M5: ='Revenue Build'!M12 | N5: ='Revenue Build'!N12 | O5: ='Revenue Build'!O12
A6: Trade receivables | B6: ='Historical BS'!B24 | C6: ='Historical BS'!C24 | D6: ='Historical BS'!D24 | E6: ='Historical BS'!E24 | F6: ='Historical BS'!F24 | G6: ='Historical BS'!G24 | H6: ='Historical BS'!H24 | I6: =I5*'Assumptions'!I27 | J6: =J5*'Assumptions'!I27 | K6: =K5*'Assumptions'!I27 | L6: =L5*'Assumptions'!I27 | M6: =M5*'Assumptions'!I27 | N6: =N5*'Assumptions'!I27 | O6: =O5*'Assumptions'!I27
A7: Inventories | B7: ='Historical BS'!B22 | C7: ='Historical BS'!C22 | D7: ='Historical BS'!D22 | E7: ='Historical BS'!E22 | F7: ='Historical BS'!F22 | G7: ='Historical BS'!G22 | H7: ='Historical BS'!H22 | I7: =I5*'Assumptions'!I28 | J7: =J5*'Assumptions'!I28 | K7: =K5*'Assumptions'!I28 | L7: =L5*'Assumptions'!I28 | M7: =M5*'Assumptions'!I28 | N7: =N5*'Assumptions'!I28 | O7: =O5*'Assumptions'!I28
A8: Other current assets | B8: ='Historical BS'!B30 | C8: ='Historical BS'!C30 | D8: ='Historical BS'!D30 | E8: ='Historical BS'!E30 | F8: ='Historical BS'!F30 | G8: ='Historical BS'!G30 | H8: ='Historical BS'!H30 | I8: =I5*'Assumptions'!I30 | J8: =J5*'Assumptions'!I30 | K8: =K5*'Assumptions'!I30 | L8: =L5*'Assumptions'!I30 | M8: =M5*'Assumptions'!I30 | N8: =N5*'Assumptions'!I30 | O8: =O5*'Assumptions'!I30
A9: Trade payables | B9: ='Historical BS'!B48 | C9: ='Historical BS'!C48 | D9: ='Historical BS'!D48 | E9: ='Historical BS'!E48 | F9: ='Historical BS'!F48 | G9: ='Historical BS'!G48 | H9: ='Historical BS'!H48 | I9: =I5*'Assumptions'!I29 | J9: =J5*'Assumptions'!I29 | K9: =K5*'Assumptions'!I29 | L9: =L5*'Assumptions'!I29 | M9: =M5*'Assumptions'!I29 | N9: =N5*'Assumptions'!I29 | O9: =O5*'Assumptions'!I29
A10: Other current liabilities | B10: ='Historical BS'!B50 | C10: ='Historical BS'!C50 | D10: ='Historical BS'!D50 | E10: ='Historical BS'!E50 | F10: ='Historical BS'!F50 | G10: ='Historical BS'!G50 | H10: ='Historical BS'!H50 | I10: =I5*'Assumptions'!I31 | J10: =J5*'Assumptions'!I31 | K10: =K5*'Assumptions'!I31 | L10: =L5*'Assumptions'!I31 | M10: =M5*'Assumptions'!I31 | N10: =N5*'Assumptions'!I31 | O10: =O5*'Assumptions'!I31
A11: Net working capital | B11: =B6+B7+B8-B9-B10 | C11: =C6+C7+C8-C9-C10 | D11: =D6+D7+D8-D9-D10 | E11: =E6+E7+E8-E9-E10 | F11: =F6+F7+F8-F9-F10 | G11: =G6+G7+G8-G9-G10 | H11: =H6+H7+H8-H9-H10 | I11: =I6+I7+I8-I9-I10 | ... O11: =O6+O7+O8-O9-O10
A12: Change in NWC (increase = cash outflow) | C12: =C11-B11 | D12: =D11-C11 | E12: =E11-D11 | F12: =F11-E11 | G12: =G11-F11 | H12: =H11-G11 | I12: =I11-H11 | J12: =J11-I11 | ... O12: =O11-N11
A13: DSO (days) | B13: =B6/B5*365 | C13: =C6/C5*365 | D13: =D6/D5*365 | E13: =E6/E5*365 | F13: =F6/F5*365 | G13: =G6/G5*365 | H13: =H6/H5*365 | I13: =I6/I5*365 | ... O13: =O6/O5*365
A14: DPO (days, on revenue) | B14: =B9/B5*365 | C14: =C9/C5*365 | D14: =D9/D5*365 | E14: =E9/E5*365 | F14: =F9/F5*365 | G14: =G9/G5*365 | H14: =H9/H5*365 | I14: =I9/I5*365 | ... O14: =O9/O5*365

Sheet Debt Schedule
A1: 18. DEBT SCHEDULE
A4: INR Crore unless stated | B4: FY20A | C4: FY21A | D4: FY22A | E4: FY23A | F4: FY24A | G4: FY25A | H4: FY26A | I4: FY27E | J4: FY28E | K4: FY29E | L4: FY30E | M4: FY31E | N4: FY32E | O4: FY33E
A5: Opening gross debt | I5: ='Historical BS'!H38+'Historical BS'!H46 | J5: =I6 | K5: =J6 | L5: =K6 | M5: =L6 | N5: =M6 | O5: =N6
A6: Closing gross debt (target) | I6: ='Assumptions'!I33 | J6: ='Assumptions'!J33 | K6: ='Assumptions'!K33 | L6: ='Assumptions'!L33 | M6: ='Assumptions'!M33 | N6: ='Assumptions'!N33 | O6: ='Assumptions'!O33
A7: Net drawdown/(repayment) | I7: =I6-I5 | J7: =J6-J5 | K7: =K6-K5 | L7: =L6-L5 | M7: =M6-M5 | N7: =N6-N5 | O7: =O6-O5
A8: Average gross debt | I8: =(I5+I6)/2 | J8: =(J5+J6)/2 | K8: =(K5+K6)/2 | L8: =(L5+L6)/2 | M8: =(M5+M6)/2 | N8: =(N5+N6)/2 | O8: =(O5+O6)/2
A9: Interest rate % | I9: ='Assumptions'!I34 | J9: ='Assumptions'!I34 | K9: ='Assumptions'!I34 | L9: ='Assumptions'!I34 | M9: ='Assumptions'!I34 | N9: ='Assumptions'!I34 | O9: ='Assumptions'!I34
A10: Borrowing interest expense | I10: =I8*I9 | J10: =J8*J9 | K10: =K8*K9 | L10: =L8*L9 | M10: =M8*M9 | N10: =N8*N9 | O10: =O8*O9
A11: Current portion (period-end) | I11: =I6*0.161 | J11: =J6*0.161 | K11: =K6*0.161 | L11: =L6*0.161 | M11: =M6*0.161 | N11: =N6*0.161 | O11: =O6*0.161
A12: Non-current portion (period-end) | I12: =I6-I11 | J12: =J6-J11 | K12: =K6-K11 | L12: =L6-L11 | M12: =M6-M11 | N12: =N6-N11 | O12: =O6-O11

Sheet Lease Schedule
A1: 19. LEASE LIABILITY SCHEDULE
A4: INR Crore unless stated | B4: FY20A | C4: FY21A | D4: FY22A | E4: FY23A | F4: FY24A | G4: FY25A | H4: FY26A | I4: FY27E | J4: FY28E | K4: FY29E | L4: FY30E | M4: FY31E | N4: FY32E | O4: FY33E
A5: Opening lease liability | I5: ='Historical BS'!H39+'Historical BS'!H47 | J5: =I9 | K5: =J9 | L5: =K9 | M5: =L9 | N5: =M9 | O5: =N9
A6: Add: new lease additions | I6: ='Assumptions'!I23 | J6: ='Assumptions'!I23 | K6: ='Assumptions'!I23 | L6: ='Assumptions'!I23 | M6: ='Assumptions'!I23 | N6: ='Assumptions'!I23 | O6: ='Assumptions'!I23
A7: Lease interest (rate x opening) | I7: =I5*'Assumptions'!I25 | J7: =J5*'Assumptions'!I25 | K7: =K5*'Assumptions'!I25 | L7: =L5*'Assumptions'!I25 | M7: =M5*'Assumptions'!I25 | N7: =N5*'Assumptions'!I25 | O7: =O5*'Assumptions'!I25
A8: Less: principal payment | I8: ='Assumptions'!I23 | J8: ='Assumptions'!I23 | K8: ='Assumptions'!I23 | L8: ='Assumptions'!I23 | M8: ='Assumptions'!I23 | N8: ='Assumptions'!I23 | O8: ='Assumptions'!I23
A9: Closing lease liability | I9: =I5+I6-I8 | J9: =J5+J6-J8 | K9: =K5+K6-K8 | L9: =L5+L6-L8 | M9: =M5+M6-M8 | N9: =N5+N6-N8 | O9: =O5+O6-O8
A11: Leases modelled at steady state (additions = principal payment = ROU depreciation) given shift toward owned assets; lease liability held ~flat. Simplification disclosed.

Sheet Tax Schedule
A1: 20. TAX SCHEDULE & EBIT / PBT / PAT BRIDGE (forecast)
A4: INR Crore unless stated | B4: FY20A | C4: FY21A | D4: FY22A | E4: FY23A | F4: FY24A | G4: FY25A | H4: FY26A | I4: FY27E | J4: FY28E | K4: FY29E | L4: FY30E | M4: FY31E | N4: FY32E | O4: FY33E
A5: PBIDT (EBITDA + other income) | I5: ='EBITDA Build'!I14 | J5: ='EBITDA Build'!J14 | K5: ='EBITDA Build'!K14 | L5: ='EBITDA Build'!L14 | M5: ='EBITDA Build'!M14 | N5: ='EBITDA Build'!N14 | O5: ='EBITDA Build'!O14
A6: Less: Depreciation & amortisation | I6: =-'PPE Depreciation'!I18 | J6: =-'PPE Depreciation'!J18 | K6: =-'PPE Depreciation'!K18 | L6: =-'PPE Depreciation'!L18 | M6: =-'PPE Depreciation'!M18 | N6: =-'PPE Depreciation'!N18 | O6: =-'PPE Depreciation'!O18
A7: EBIT | I7: =I5+I6 | J7: =J5+J6 | K7: =K5+K6 | L7: =L5+L6 | M7: =M5+M6 | N7: =N5+N6 | O7: =O5+O6
A8: Less: Finance cost (debt + lease) | I8: =-('Debt Schedule'!I10+'Lease Schedule'!I7) | J8: =-('Debt Schedule'!J10+'Lease Schedule'!J7) | K8: =-('Debt Schedule'!K10+'Lease Schedule'!K7) | L8: =-('Debt Schedule'!L10+'Lease Schedule'!L7) | M8: =-('Debt Schedule'!M10+'Lease Schedule'!M7) | N8: =-('Debt Schedule'!N10+'Lease Schedule'!N7) | O8: =-('Debt Schedule'!O10+'Lease Schedule'!O7)
A9: Profit before tax | I9: =I7+I8 | J9: =J7+J8 | K9: =K7+K8 | L9: =L7+L8 | M9: =M7+M8 | N9: =N7+N8 | O9: =O7+O8
A10: Effective tax rate % | I10: ='Assumptions'!I35 | J10: ='Assumptions'!I35 | K10: ='Assumptions'!I35 | L10: ='Assumptions'!I35 | M10: ='Assumptions'!I35 | N10: ='Assumptions'!I35 | O10: ='Assumptions'!I35
A11: Tax expense | I11: =I9*I10 | J11: =J9*J10 | K11: =K9*K10 | L11: =L9*L10 | M11: =M9*M10 | N11: =N9*N10 | O11: =O9*O10
A12: Profit after tax | I12: =I9-I11 | J12: =J9-J11 | K12: =K9-K11 | L12: =L9-L11 | M12: =M9-M11 | N12: =N9-N11 | O12: =O9-O11

Sheet Integrated IS
A1: 21. INTEGRATED INCOME STATEMENT (FY20A-FY33E)
A4: INR Crore unless stated | B4: FY20A | C4: FY21A | D4: FY22A | E4: FY23A | F4: FY24A | G4: FY25A | H4: FY26A | I4: FY27E | J4: FY28E | K4: FY29E | L4: FY30E | M4: FY31E | N4: FY32E | O4: FY33E
A5: Revenue from operations | B5: ='Historical P&L'!B5 | C5: ='Historical P&L'!C5 | D5: ='Historical P&L'!D5 | E5: ='Historical P&L'!E5 | F5: ='Historical P&L'!F5 | G5: ='Historical P&L'!G5 | H5: ='Historical P&L'!H5 | I5: ='Revenue Build'!I12 | J5: ='Revenue Build'!J12 | K5: ='Revenue Build'!K12 | L5: ='Revenue Build'!L12 | M5: ='Revenue Build'!M12 | N5: ='Revenue Build'!N12 | O5: ='Revenue Build'!O12
A6: Other income | B6: ='Historical P&L'!B6 | C6: ='Historical P&L'!C6 | D6: ='Historical P&L'!D6 | E6: ='Historical P&L'!E6 | F6: ='Historical P&L'!F6 | G6: ='Historical P&L'!G6 | H6: ='Historical P&L'!H6 | I6: ='EBITDA Build'!I13 | J6: ='EBITDA Build'!J13 | K6: ='EBITDA Build'!K13 | L6: ='EBITDA Build'!L13 | M6: ='EBITDA Build'!M13 | N6: ='EBITDA Build'!N13 | O6: ='EBITDA Build'!O13
A7: Total income | B7: =B5+B6 | C7: =C5+C6 | D7: =D5+D6 | E7: =E5+E6 | F7: =F5+F6 | G7: =G5+G6 | H7: =H5+H6 | I7: =I5+I6 | ... O7: =O5+O6
A8: Direct cost (drugs/consumables, net) | B8: ='Historical P&L'!B25 | C8: ='Historical P&L'!C25 | D8: ='Historical P&L'!D25 | E8: ='Historical P&L'!E25 | F8: ='Historical P&L'!F25 | G8: ='Historical P&L'!G25 | H8: ='Historical P&L'!H25 | I8: ='Direct Cost GP'!I7 | J8: ='Direct Cost GP'!J7 | K8: ='Direct Cost GP'!K7 | L8: ='Direct Cost GP'!L7 | M8: ='Direct Cost GP'!M7 | N8: ='Direct Cost GP'!N7 | O8: ='Direct Cost GP'!O7
A9: Employee benefits expense | B9: ='Historical P&L'!B11 | C9: ='Historical P&L'!C11 | D9: ='Historical P&L'!D11 | E9: ='Historical P&L'!E11 | F9: ='Historical P&L'!F11 | G9: ='Historical P&L'!G11 | H9: ='Historical P&L'!H11 | I9: ='Opex Build'!I7 | J9: ='Opex Build'!J7 | K9: ='Opex Build'!K7 | L9: ='Opex Build'!L7 | M9: ='Opex Build'!M7 | N9: ='Opex Build'!N7 | O9: ='Opex Build'!O7
A10: Professional & consultancy fee | B10: ='Historical P&L'!B12 | C10: ='Historical P&L'!C12 | D10: ='Historical P&L'!D12 | E10: ='Historical P&L'!E12 | F10: ='Historical P&L'!F12 | G10: ='Historical P&L'!G12 | H10: ='Historical P&L'!H12 | I10: ='Opex Build'!I9 | J10: ='Opex Build'!J9 | K10: ='Opex Build'!K9 | L10: ='Opex Build'!L9 | M10: ='Opex Build'!M9 | N10: ='Opex Build'!N9 | O10: ='Opex Build'!O9
A11: Other operating expenses | B11: ='Historical P&L'!B13 | C11: ='Historical P&L'!C13 | D11: ='Historical P&L'!D13 | E11: ='Historical P&L'!E13 | F11: ='Historical P&L'!F13 | G11: ='Historical P&L'!G13 | H11: ='Historical P&L'!H13 | I11: ='Opex Build'!I11 | J11: ='Opex Build'!J11 | K11: ='Opex Build'!K11 | L11: ='Opex Build'!L11 | M11: ='Opex Build'!M11 | N11: ='Opex Build'!N11 | O11: ='Opex Build'!O11
A12: Analytical Gross Profit | B12: =B5-B8 | C12: =C5-C8 | D12: =D5-D8 | E12: =E5-E8 | F12: =F5-F8 | G12: =G5-G8 | H12: =H5-H8 | I12: =I5-I8 | ... O12: =O5-O8
A13: EBITDA (excl. other income) | B13: =B5-B8-B9-B10-B11 | C13: =C5-C8-C9-C10-C11 | D13: =D5-D8-D9-D10-D11 | E13: =E5-E8-E9-E10-E11 | F13: =F5-F8-F9-F10-F11 | G13: =G5-G8-G9-G10-G11 | H13: =H5-H8-H9-H10-H11 | I13: =I5-I8-I9-I10-I11 | ... O13: =O5-O8-O9-O10-O11
A14: EBITDA margin % | B14: =B13/B5 | C14: =C13/C5 | D14: =D13/D5 | E14: =E13/E5 | F14: =F13/F5 | G14: =G13/G5 | H14: =H13/H5 | I14: =I13/I5 | ... O14: =O13/O5
A15: PBIDT (EBITDA + other income) | B15: =B13+B6 | C15: =C13+C6 | D15: =D13+D6 | E15: =E13+E6 | F15: =F13+F6 | G15: =G13+G6 | H15: =H13+H6 | I15: =I13+I6 | ... O15: =O13+O6
A16: Depreciation & amortisation | B16: ='Historical P&L'!B15 | C16: ='Historical P&L'!C15 | D16: ='Historical P&L'!D15 | E16: ='Historical P&L'!E15 | F16: ='Historical P&L'!F15 | G16: ='Historical P&L'!G15 | H16: ='Historical P&L'!H15 | I16: ='PPE Depreciation'!I18 | J16: ='PPE Depreciation'!J18 | K16: ='PPE Depreciation'!K18 | L16: ='PPE Depreciation'!L18 | M16: ='PPE Depreciation'!M18 | N16: ='PPE Depreciation'!N18 | O16: ='PPE Depreciation'!O18
A17: EBIT | B17: =B15-B16 | C17: =C15-C16 | D17: =D15-D16 | E17: =E15-E16 | F17: =F15-F16 | G17: =G15-G16 | H17: =H15-H16 | I17: =I15-I16 | ... O17: =O15-O16
A18: Finance costs | B18: ='Historical P&L'!B14 | C18: ='Historical P&L'!C14 | D18: ='Historical P&L'!D14 | E18: ='Historical P&L'!E14 | F18: ='Historical P&L'!F14 | G18: ='Historical P&L'!G14 | H18: ='Historical P&L'!H14 | I18: ='Debt Schedule'!I10+'Lease Schedule'!I7 | J18: ='Debt Schedule'!J10+'Lease Schedule'!J7 | K18: ='Debt Schedule'!K10+'Lease Schedule'!K7 | L18: ='Debt Schedule'!L10+'Lease Schedule'!L7 | M18: ='Debt Schedule'!M10+'Lease Schedule'!M7 | N18: ='Debt Schedule'!N10+'Lease Schedule'!N7 | O18: ='Debt Schedule'!O10+'Lease Schedule'!O7
A19: PBT before exceptional | B19: =B17-B18 | C19: =C17-C18 | D19: =D17-D18 | E19: =E17-E18 | F19: =F17-F18 | G19: =G17-G18 | H19: =H17-H18 | I19: =I17-I18 | ... O19: =O17-O18
A20: Exceptional items | B20: ='Historical P&L'!B18 | C20: ='Historical P&L'!C18 | D20: ='Historical P&L'!D18 | E20: ='Historical P&L'!E18 | F20: ='Historical P&L'!F18 | G20: ='Historical P&L'!G18 | H20: ='Historical P&L'!H18 | I20: 0 | J20: 0 | K20: 0 | L20: 0 | M20: 0 | N20: 0 | O20: 0
A21: Profit before tax | B21: =B19+B20 | C21: =C19+C20 | D21: =D19+D20 | E21: =E19+E20 | F21: =F19+F20 | G21: =G19+G20 | H21: =H19+H20 | I21: =I19+I20 | ... O21: =O19+O20
A22: Tax expense | B22: ='Historical P&L'!B20 | C22: ='Historical P&L'!C20 | D22: ='Historical P&L'!D20 | E22: ='Historical P&L'!E20 | F22: ='Historical P&L'!F20 | G22: ='Historical P&L'!G20 | H22: ='Historical P&L'!H20 | I22: ='Tax Schedule'!I11 | J22: ='Tax Schedule'!J11 | K22: ='Tax Schedule'!K11 | L22: ='Tax Schedule'!L11 | M22: ='Tax Schedule'!M11 | N22: ='Tax Schedule'!N11 | O22: ='Tax Schedule'!O11
A23: PAT before share of associate | B23: =B21-B22 | C23: =C21-C22 | D23: =D21-D22 | E23: =E21-E22 | F23: =F21-F22 | G23: =G21-G22 | H23: =H21-H22 | I23: =I21-I22 | ... O23: =O21-O22
A24: Share of profit in associate | B24: ='Historical P&L'!B22 | C24: ='Historical P&L'!C22 | D24: ='Historical P&L'!D22 | E24: ='Historical P&L'!E22 | F24: ='Historical P&L'!F22 | G24: ='Historical P&L'!G22 | H24: ='Historical P&L'!H22 | I24: 0 | J24: 0 | K24: 0 | L24: 0 | M24: 0 | N24: 0 | O24: 0
A25: Profit for the year (PAT) | B25: =B23+B24 | C25: =C23+C24 | D25: =D23+D24 | E25: =E23+E24 | F25: =F23+F24 | G25: =G23+G24 | H25: =H23+H24 | I25: =I23+I24 | ... O25: =O23+O24
A26: PAT margin % | B26: =B25/B5 | C26: =C25/C5 | D26: =D25/D5 | E26: =E25/E5 | F26: =F25/F5 | G26: =G25/G5 | H26: =H25/H5 | I26: =I25/I5 | ... O26: =O25/O5
A27: EPS (Rs) | B27: =B25/'Assumptions'!I44 | C27: =C25/'Assumptions'!I44 | D27: =D25/'Assumptions'!I44 | E27: =E25/'Assumptions'!I44 | F27: =F25/'Assumptions'!I44 | G27: =G25/'Assumptions'!I44 | H27: =H25/'Assumptions'!I44 | I27: =I25/'Assumptions'!I44 | J27: =J25/'Assumptions'!I44 | K27: =K25/'Assumptions'!I44 | L27: =L25/'Assumptions'!I44 | M27: =M25/'Assumptions'!I44 | N27: =N25/'Assumptions'!I44 | O27: =O25/'Assumptions'!I44
A28: Revenue growth % | C28: =C5/B5-1 | D28: =D5/C5-1 | E28: =E5/D5-1 | F28: =F5/E5-1 | G28: =G5/F5-1 | H28: =H5/G5-1 | I28: =I5/H5-1 | J28: =J5/I5-1 | ... O28: =O5/N5-1

Sheet Integrated BS
A1: 22. INTEGRATED BALANCE SHEET (FY20A-FY33E)
A4: INR Crore unless stated | B4: FY20A | C4: FY21A | D4: FY22A | E4: FY23A | F4: FY24A | G4: FY25A | H4: FY26A | I4: FY27E | J4: FY28E | K4: FY29E | L4: FY30E | M4: FY31E | N4: FY32E | O4: FY33E
A5: ASSETS - Non-current
A6: Property, plant & equipment | B6: ='Historical BS'!B6 | C6: ='Historical BS'!C6 | D6: ='Historical BS'!D6 | E6: ='Historical BS'!E6 | F6: ='Historical BS'!F6 | G6: ='Historical BS'!G6 | H6: ='Historical BS'!H6 | I6: ='PPE Depreciation'!I9 | J6: ='PPE Depreciation'!J9 | K6: ='PPE Depreciation'!K9 | L6: ='PPE Depreciation'!L9 | M6: ='PPE Depreciation'!M9 | N6: ='PPE Depreciation'!N9 | O6: ='PPE Depreciation'!O9
A7: Right-of-use assets | B7: ='Historical BS'!B7 | C7: ='Historical BS'!C7 | D7: ='Historical BS'!D7 | E7: ='Historical BS'!E7 | F7: ='Historical BS'!F7 | G7: ='Historical BS'!G7 | H7: ='Historical BS'!H7 | I7: ='PPE Depreciation'!I14 | J7: ='PPE Depreciation'!J14 | K7: ='PPE Depreciation'!K14 | L7: ='PPE Depreciation'!L14 | M7: ='PPE Depreciation'!M14 | N7: ='PPE Depreciation'!N14 | O7: ='PPE Depreciation'!O14
A8: Capital work-in-progress | B8: ='Historical BS'!B8 | C8: ='Historical BS'!C8 | D8: ='Historical BS'!D8 | E8: ='Historical BS'!E8 | F8: ='Historical BS'!F8 | G8: ='Historical BS'!G8 | H8: ='Historical BS'!H8 | I8: ='Historical BS'!H8 | J8: ='Historical BS'!H8 | K8: ='Historical BS'!H8 | L8: ='Historical BS'!H8 | M8: ='Historical BS'!H8 | N8: ='Historical BS'!H8 | O8: ='Historical BS'!H8
A9: Investment property | B9: ='Historical BS'!B9 | C9: ='Historical BS'!C9 | D9: ='Historical BS'!D9 | E9: ='Historical BS'!E9 | F9: ='Historical BS'!F9 | G9: ='Historical BS'!G9 | H9: ='Historical BS'!H9 | I9: ='Historical BS'!H9 | J9: ='Historical BS'!H9 | K9: ='Historical BS'!H9 | L9: ='Historical BS'!H9 | M9: ='Historical BS'!H9 | N9: ='Historical BS'!H9 | O9: ='Historical BS'!H9
A10: Goodwill | B10: ='Historical BS'!B10 | C10: ='Historical BS'!C10 | D10: ='Historical BS'!D10 | E10: ='Historical BS'!E10 | F10: ='Historical BS'!F10 | G10: ='Historical BS'!G10 | H10: ='Historical BS'!H10 | I10: ='Historical BS'!H10 | J10: ='Historical BS'!H10 | K10: ='Historical BS'!H10 | L10: ='Historical BS'!H10 | M10: ='Historical BS'!H10 | N10: ='Historical BS'!H10 | O10: ='Historical BS'!H10
A11: Other intangible assets | B11: ='Historical BS'!B11 | C11: ='Historical BS'!C11 | D11: ='Historical BS'!D11 | E11: ='Historical BS'!E11 | F11: ='Historical BS'!F11 | G11: ='Historical BS'!G11 | H11: ='Historical BS'!H11 | I11: ='PPE Depreciation'!I17 | J11: ='PPE Depreciation'!J17 | K11: ='PPE Depreciation'!K17 | L11: ='PPE Depreciation'!L17 | M11: ='PPE Depreciation'!M17 | N11: ='PPE Depreciation'!N17 | O11: ='PPE Depreciation'!O17
A12: Intangible assets under development | B12: ='Historical BS'!B12 | C12: ='Historical BS'!C12 | D12: ='Historical BS'!D12 | E12: ='Historical BS'!E12 | F12: ='Historical BS'!F12 | G12: ='Historical BS'!G12 | H12: ='Historical BS'!H12 | I12: ='Historical BS'!H12 | J12: ='Historical BS'!H12 | K12: ='Historical BS'!H12 | L12: ='Historical BS'!H12 | M12: ='Historical BS'!H12 | N12: ='Historical BS'!H12 | O12: ='Historical BS'!H12
A13: Investments (non-current) | B13: ='Historical BS'!B13 | C13: ='Historical BS'!C13 | D13: ='Historical BS'!D13 | E13: ='Historical BS'!E13 | F13: ='Historical BS'!F13 | G13: ='Historical BS'!G13 | H13: ='Historical BS'!H13 | I13: ='Historical BS'!H13 | J13: ='Historical BS'!H13 | K13: ='Historical BS'!H13 | L13: ='Historical BS'!H13 | M13: ='Historical BS'!H13 | N13: ='Historical BS'!H13 | O13: ='Historical BS'!H13
A14: Trade receivables (non-current) | B14: ='Historical BS'!B14 | C14: ='Historical BS'!C14 | D14: ='Historical BS'!D14 | E14: ='Historical BS'!E14 | F14: ='Historical BS'!F14 | G14: ='Historical BS'!G14 | H14: ='Historical BS'!H14 | I14: ='Historical BS'!H14 | J14: ='Historical BS'!H14 | K14: ='Historical BS'!H14 | L14: ='Historical BS'!H14 | M14: ='Historical BS'!H14 | N14: ='Historical BS'!H14 | O14: ='Historical BS'!H14
A15: Loans (non-current) | B15: ='Historical BS'!B15 | C15: ='Historical BS'!C15 | D15: ='Historical BS'!D15 | E15: ='Historical BS'!E15 | F15: ='Historical BS'!F15 | G15: ='Historical BS'!G15 | H15: ='Historical BS'!H15 | I15: ='Historical BS'!H15 | J15: ='Historical BS'!H15 | K15: ='Historical BS'!H15 | L15: ='Historical BS'!H15 | M15: ='Historical BS'!H15 | N15: ='Historical BS'!H15 | O15: ='Historical BS'!H15
A16: Other financial assets (non-current) | B16: ='Historical BS'!B16 | C16: ='Historical BS'!C16 | D16: ='Historical BS'!D16 | E16: ='Historical BS'!E16 | F16: ='Historical BS'!F16 | G16: ='Historical BS'!G16 | H16: ='Historical BS'!H16 | I16: ='Historical BS'!H16 | J16: ='Historical BS'!H16 | K16: ='Historical BS'!H16 | L16: ='Historical BS'!H16 | M16: ='Historical BS'!H16 | N16: ='Historical BS'!H16 | O16: ='Historical BS'!H16
A17: Income tax assets (net) | B17: ='Historical BS'!B17 | C17: ='Historical BS'!C17 | D17: ='Historical BS'!D17 | E17: ='Historical BS'!E17 | F17: ='Historical BS'!F17 | G17: ='Historical BS'!G17 | H17: ='Historical BS'!H17 | I17: ='Historical BS'!H17 | J17: ='Historical BS'!H17 | K17: ='Historical BS'!H17 | L17: ='Historical BS'!H17 | M17: ='Historical BS'!H17 | N17: ='Historical BS'!H17 | O17: ='Historical BS'!H17
A18: Deferred tax assets (net) | B18: ='Historical BS'!B18 | C18: ='Historical BS'!C18 | D18: ='Historical BS'!D18 | E18: ='Historical BS'!E18 | F18: ='Historical BS'!F18 | G18: ='Historical BS'!G18 | H18: ='Historical BS'!H18 | I18: ='Historical BS'!H18 | J18: ='Historical BS'!H18 | K18: ='Historical BS'!H18 | L18: ='Historical BS'!H18 | M18: ='Historical BS'!H18 | N18: ='Historical BS'!H18 | O18: ='Historical BS'!H18
A19: Other non-current assets | B19: ='Historical BS'!B19 | C19: ='Historical BS'!C19 | D19: ='Historical BS'!D19 | E19: ='Historical BS'!E19 | F19: ='Historical BS'!F19 | G19: ='Historical BS'!G19 | H19: ='Historical BS'!H19 | I19: ='Historical BS'!H19 | J19: ='Historical BS'!H19 | K19: ='Historical BS'!H19 | L19: ='Historical BS'!H19 | M19: ='Historical BS'!H19 | N19: ='Historical BS'!H19 | O19: ='Historical BS'!H19
A20: Total non-current assets | B20: =B6+B7+B8+B9+B10+B11+B12+B13+B14+B15+B16+B17+B18+B19 | C20: =C6+C7+C8+C9+C10+C11+C12+C13+C14+C15+C16+C17+C18+C19 | D20: =D6+D7+D8+D9+D10+D11+D12+D13+D14+D15+D16+D17+D18+D19 | E20: =E6+E7+E8+E9+E10+E11+E12+E13+E14+E15+E16+E17+E18+E19 | F20: =F6+F7+F8+F9+F10+F11+F12+F13+F14+F15+F16+F17+F18+F19 | G20: =G6+G7+G8+G9+G10+G11+G12+G13+G14+G15+G16+G17+G18+G19 | H20: =H6+H7+H8+H9+H10+H11+H12+H13+H14+H15+H16+H17+H18+H19 | I20: =I6+I7+I8+I9+I10+I11+I12+I13+I14+I15+I16+I17+I18+I19 | ... O20: =O6+O7+O8+O9+O10+O11+O12+O13+O14+O15+O16+O17+O18+O19
A21: Current assets
A22: Inventories | B22: ='Historical BS'!B22 | C22: ='Historical BS'!C22 | D22: ='Historical BS'!D22 | E22: ='Historical BS'!E22 | F22: ='Historical BS'!F22 | G22: ='Historical BS'!G22 | H22: ='Historical BS'!H22 | I22: ='Working Capital'!I7 | J22: ='Working Capital'!J7 | K22: ='Working Capital'!K7 | L22: ='Working Capital'!L7 | M22: ='Working Capital'!M7 | N22: ='Working Capital'!N7 | O22: ='Working Capital'!O7
A23: Investments (current) | B23: ='Historical BS'!B23 | C23: ='Historical BS'!C23 | D23: ='Historical BS'!D23 | E23: ='Historical BS'!E23 | F23: ='Historical BS'!F23 | G23: ='Historical BS'!G23 | H23: ='Historical BS'!H23 | I23: ='Historical BS'!H23 | J23: ='Historical BS'!H23 | K23: ='Historical BS'!H23 | L23: ='Historical BS'!H23 | M23: ='Historical BS'!H23 | N23: ='Historical BS'!H23 | O23: ='Historical BS'!H23
A24: Trade receivables (current) | B24: ='Historical BS'!B24 | C24: ='Historical BS'!C24 | D24: ='Historical BS'!D24 | E24: ='Historical BS'!E24 | F24: ='Historical BS'!F24 | G24: ='Historical BS'!G24 | H24: ='Historical BS'!H24 | I24: ='Working Capital'!I6 | J24: ='Working Capital'!J6 | K24: ='Working Capital'!K6 | L24: ='Working Capital'!L6 | M24: ='Working Capital'!M6 | N24: ='Working Capital'!N6 | O24: ='Working Capital'!O6
A25: Cash & cash equivalents | B25: ='Historical BS'!B25 | C25: ='Historical BS'!C25 | D25: ='Historical BS'!D25 | E25: ='Historical BS'!E25 | F25: ='Historical BS'!F25 | G25: ='Historical BS'!G25 | H25: ='Historical BS'!H25 | I25: ='Integrated CF'!I22 | J25: ='Integrated CF'!J22 | K25: ='Integrated CF'!K22 | L25: ='Integrated CF'!L22 | M25: ='Integrated CF'!M22 | N25: ='Integrated CF'!N22 | O25: ='Integrated CF'!O22
A26: Bank balances other | B26: ='Historical BS'!B26 | C26: ='Historical BS'!C26 | D26: ='Historical BS'!D26 | E26: ='Historical BS'!E26 | F26: ='Historical BS'!F26 | G26: ='Historical BS'!G26 | H26: ='Historical BS'!H26 | I26: ='Historical BS'!H26 | J26: ='Historical BS'!H26 | K26: ='Historical BS'!H26 | L26: ='Historical BS'!H26 | M26: ='Historical BS'!H26 | N26: ='Historical BS'!H26 | O26: ='Historical BS'!H26
A27: Loans (current) | B27: ='Historical BS'!B27 | C27: ='Historical BS'!C27 | D27: ='Historical BS'!D27 | E27: ='Historical BS'!E27 | F27: ='Historical BS'!F27 | G27: ='Historical BS'!G27 | H27: ='Historical BS'!H27 | I27: ='Historical BS'!H27 | J27: ='Historical BS'!H27 | K27: ='Historical BS'!H27 | L27: ='Historical BS'!H27 | M27: ='Historical BS'!H27 | N27: ='Historical BS'!H27 | O27: ='Historical BS'!H27
A28: Other financial assets (current) | B28: ='Historical BS'!B28 | C28: ='Historical BS'!C28 | D28: ='Historical BS'!D28 | E28: ='Historical BS'!E28 | F28: ='Historical BS'!F28 | G28: ='Historical BS'!G28 | H28: ='Historical BS'!H28 | I28: ='Historical BS'!H28 | J28: ='Historical BS'!H28 | K28: ='Historical BS'!H28 | L28: ='Historical BS'!H28 | M28: ='Historical BS'!H28 | N28: ='Historical BS'!H28 | O28: ='Historical BS'!H28
A29: Income tax assets (current) | B29: ='Historical BS'!B29 | C29: ='Historical BS'!C29 | D29: ='Historical BS'!D29 | E29: ='Historical BS'!E29 | F29: ='Historical BS'!F29 | G29: ='Historical BS'!G29 | H29: ='Historical BS'!H29 | I29: ='Historical BS'!H29 | J29: ='Historical BS'!H29 | K29: ='Historical BS'!H29 | L29: ='Historical BS'!H29 | M29: ='Historical BS'!H29 | N29: ='Historical BS'!H29 | O29: ='Historical BS'!H29
A30: Other current assets | B30: ='Historical BS'!B30 | C30: ='Historical BS'!C30 | D30: ='Historical BS'!D30 | E30: ='Historical BS'!E30 | F30: ='Historical BS'!F30 | G30: ='Historical BS'!G30 | H30: ='Historical BS'!H30 | I30: ='Working Capital'!I8 | J30: ='Working Capital'!J8 | K30: ='Working Capital'!K8 | L30: ='Working Capital'!L8 | M30: ='Working Capital'!M8 | N30: ='Working Capital'!N8 | O30: ='Working Capital'!O8
A31: Total current assets | B31: =B22+B23+B24+B25+B26+B27+B28+B29+B30 | C31: =C22+C23+C24+C25+C26+C27+C28+C29+C30 | D31: =D22+D23+D24+D25+D26+D27+D28+D29+D30 | E31: =E22+E23+E24+E25+E26+E27+E28+E29+E30 | F31: =F22+F23+F24+F25+F26+F27+F28+F29+F30 | G31: =G22+G23+G24+G25+G26+G27+G28+G29+G30 | H31: =H22+H23+H24+H25+H26+H27+H28+H29+H30 | I31: =I22+I23+I24+I25+I26+I27+I28+I29+I30 | ... O31: =O22+O23+O24+O25+O26+O27+O28+O29+O30
A32: TOTAL ASSETS | B32: =B20+B31 | C32: =C20+C31 | D32: =D20+D31 | E32: =E20+E31 | F32: =F20+F31 | G32: =G20+G31 | H32: =H20+H31 | I32: =I20+I31 | ... O32: =O20+O31
A33: EQUITY
A34: Equity share capital | B34: ='Historical BS'!B34 | C34: ='Historical BS'!C34 | D34: ='Historical BS'!D34 | E34: ='Historical BS'!E34 | F34: ='Historical BS'!F34 | G34: ='Historical BS'!G34 | H34: ='Historical BS'!H34 | I34: ='Historical BS'!H34 | J34: ='Historical BS'!H34 | K34: ='Historical BS'!H34 | L34: ='Historical BS'!H34 | M34: ='Historical BS'!H34 | N34: ='Historical BS'!H34 | O34: ='Historical BS'!H34
A35: Other equity | B35: ='Historical BS'!B35 | C35: ='Historical BS'!C35 | D35: ='Historical BS'!D35 | E35: ='Historical BS'!E35 | F35: ='Historical BS'!F35 | G35: ='Historical BS'!G35 | H35: ='Historical BS'!H35 | I35: ='Historical BS'!H35+'Integrated IS'!I25+'Integrated CF'!I17 | J35: =I35+'Integrated IS'!J25+'Integrated CF'!J17 | K35: =J35+'Integrated IS'!K25+'Integrated CF'!K17 | L35: =K35+'Integrated IS'!L25+'Integrated CF'!L17 | M35: =L35+'Integrated IS'!M25+'Integrated CF'!M17 | N35: =M35+'Integrated IS'!N25+'Integrated CF'!N17 | O35: =N35+'Integrated IS'!O25+'Integrated CF'!O17
A36: Total equity | B36: =B34+B35 | C36: =C34+C35 | D36: =D34+D35 | E36: =E34+E35 | F36: =F34+F35 | G36: =G34+G35 | H36: =H34+H35 | I36: =I34+I35 | ... O36: =O34+O35
A37: Non-current liabilities
A38: Borrowings | B38: ='Historical BS'!B38 | C38: ='Historical BS'!C38 | D38: ='Historical BS'!D38 | E38: ='Historical BS'!E38 | F38: ='Historical BS'!F38 | G38: ='Historical BS'!G38 | H38: ='Historical BS'!H38 | I38: ='Debt Schedule'!I12 | J38: ='Debt Schedule'!J12 | K38: ='Debt Schedule'!K12 | L38: ='Debt Schedule'!L12 | M38: ='Debt Schedule'!M12 | N38: ='Debt Schedule'!N12 | O38: ='Debt Schedule'!O12
A39: Lease liabilities | B39: ='Historical BS'!B39 | C39: ='Historical BS'!C39 | D39: ='Historical BS'!D39 | E39: ='Historical BS'!E39 | F39: ='Historical BS'!F39 | G39: ='Historical BS'!G39 | H39: ='Historical BS'!H39 | I39: ='Historical BS'!H39 | J39: ='Historical BS'!H39 | K39: ='Historical BS'!H39 | L39: ='Historical BS'!H39 | M39: ='Historical BS'!H39 | N39: ='Historical BS'!H39 | O39: ='Historical BS'!H39
A40: Other financial liabilities | B40: ='Historical BS'!B40 | C40: ='Historical BS'!C40 | D40: ='Historical BS'!D40 | E40: ='Historical BS'!E40 | F40: ='Historical BS'!F40 | G40: ='Historical BS'!G40 | H40: ='Historical BS'!H40 | I40: ='Historical BS'!H40 | J40: ='Historical BS'!H40 | K40: ='Historical BS'!H40 | L40: ='Historical BS'!H40 | M40: ='Historical BS'!H40 | N40: ='Historical BS'!H40 | O40: ='Historical BS'!H40
A41: Provisions | B41: ='Historical BS'!B41 | C41: ='Historical BS'!C41 | D41: ='Historical BS'!D41 | E41: ='Historical BS'!E41 | F41: ='Historical BS'!F41 | G41: ='Historical BS'!G41 | H41: ='Historical BS'!H41 | I41: ='Historical BS'!H41 | J41: ='Historical BS'!H41 | K41: ='Historical BS'!H41 | L41: ='Historical BS'!H41 | M41: ='Historical BS'!H41 | N41: ='Historical BS'!H41 | O41: ='Historical BS'!H41
A42: Deferred tax liabilities (net) | B42: ='Historical BS'!B42 | C42: ='Historical BS'!C42 | D42: ='Historical BS'!D42 | E42: ='Historical BS'!E42 | F42: ='Historical BS'!F42 | G42: ='Historical BS'!G42 | H42: ='Historical BS'!H42 | I42: ='Historical BS'!H42 | J42: ='Historical BS'!H42 | K42: ='Historical BS'!H42 | L42: ='Historical BS'!H42 | M42: ='Historical BS'!H42 | N42: ='Historical BS'!H42 | O42: ='Historical BS'!H42
A43: Other non-current liabilities | B43: ='Historical BS'!B43 | C43: ='Historical BS'!C43 | D43: ='Historical BS'!D43 | E43: ='Historical BS'!E43 | F43: ='Historical BS'!F43 | G43: ='Historical BS'!G43 | H43: ='Historical BS'!H43 | I43: ='Historical BS'!H43 | J43: ='Historical BS'!H43 | K43: ='Historical BS'!H43 | L43: ='Historical BS'!H43 | M43: ='Historical BS'!H43 | N43: ='Historical BS'!H43 | O43: ='Historical BS'!H43
A44: Total non-current liabilities | B44: =B38+B39+B40+B41+B42+B43 | C44: =C38+C39+C40+C41+C42+C43 | D44: =D38+D39+D40+D41+D42+D43 | E44: =E38+E39+E40+E41+E42+E43 | F44: =F38+F39+F40+F41+F42+F43 | G44: =G38+G39+G40+G41+G42+G43 | H44: =H38+H39+H40+H41+H42+H43 | I44: =I38+I39+I40+I41+I42+I43 | ... O44: =O38+O39+O40+O41+O42+O43
A45: Current liabilities
A46: Borrowings | B46: ='Historical BS'!B46 | C46: ='Historical BS'!C46 | D46: ='Historical BS'!D46 | E46: ='Historical BS'!E46 | F46: ='Historical BS'!F46 | G46: ='Historical BS'!G46 | H46: ='Historical BS'!H46 | I46: ='Debt Schedule'!I11 | J46: ='Debt Schedule'!J11 | K46: ='Debt Schedule'!K11 | L46: ='Debt Schedule'!L11 | M46: ='Debt Schedule'!M11 | N46: ='Debt Schedule'!N11 | O46: ='Debt Schedule'!O11
A47: Lease liabilities | B47: ='Historical BS'!B47 | C47: ='Historical BS'!C47 | D47: ='Historical BS'!D47 | E47: ='Historical BS'!E47 | F47: ='Historical BS'!F47 | G47: ='Historical BS'!G47 | H47: ='Historical BS'!H47 | I47: ='Historical BS'!H47 | J47: ='Historical BS'!H47 | K47: ='Historical BS'!H47 | L47: ='Historical BS'!H47 | M47: ='Historical BS'!H47 | N47: ='Historical BS'!H47 | O47: ='Historical BS'!H47
A48: Trade payables | B48: ='Historical BS'!B48 | C48: ='Historical BS'!C48 | D48: ='Historical BS'!D48 | E48: ='Historical BS'!E48 | F48: ='Historical BS'!F48 | G48: ='Historical BS'!G48 | H48: ='Historical BS'!H48 | I48: ='Working Capital'!I9 | J48: ='Working Capital'!J9 | K48: ='Working Capital'!K9 | L48: ='Working Capital'!L9 | M48: ='Working Capital'!M9 | N48: ='Working Capital'!N9 | O48: ='Working Capital'!O9
A49: Other financial liabilities | B49: ='Historical BS'!B49 | C49: ='Historical BS'!C49 | D49: ='Historical BS'!D49 | E49: ='Historical BS'!E49 | F49: ='Historical BS'!F49 | G49: ='Historical BS'!G49 | H49: ='Historical BS'!H49 | I49: ='Historical BS'!H49 | J49: ='Historical BS'!H49 | K49: ='Historical BS'!H49 | L49: ='Historical BS'!H49 | M49: ='Historical BS'!H49 | N49: ='Historical BS'!H49 | O49: ='Historical BS'!H49
A50: Other current liabilities | B50: ='Historical BS'!B50 | C50: ='Historical BS'!C50 | D50: ='Historical BS'!D50 | E50: ='Historical BS'!E50 | F50: ='Historical BS'!F50 | G50: ='Historical BS'!G50 | H50: ='Historical BS'!H50 | I50: ='Working Capital'!I10 | J50: ='Working Capital'!J10 | K50: ='Working Capital'!K10 | L50: ='Working Capital'!L10 | M50: ='Working Capital'!M10 | N50: ='Working Capital'!N10 | O50: ='Working Capital'!O10
A51: Provisions | B51: ='Historical BS'!B51 | C51: ='Historical BS'!C51 | D51: ='Historical BS'!D51 | E51: ='Historical BS'!E51 | F51: ='Historical BS'!F51 | G51: ='Historical BS'!G51 | H51: ='Historical BS'!H51 | I51: ='Historical BS'!H51 | J51: ='Historical BS'!H51 | K51: ='Historical BS'!H51 | L51: ='Historical BS'!H51 | M51: ='Historical BS'!H51 | N51: ='Historical BS'!H51 | O51: ='Historical BS'!H51
A52: Total current liabilities | B52: =B46+B47+B48+B49+B50+B51 | C52: =C46+C47+C48+C49+C50+C51 | D52: =D46+D47+D48+D49+D50+D51 | E52: =E46+E47+E48+E49+E50+E51 | F52: =F46+F47+F48+F49+F50+F51 | G52: =G46+G47+G48+G49+G50+G51 | H52: =H46+H47+H48+H49+H50+H51 | I52: =I46+I47+I48+I49+I50+I51 | ... O52: =O46+O47+O48+O49+O50+O51
A53: Total liabilities | B53: =B44+B52 | C53: =C44+C52 | D53: =D44+D52 | E53: =E44+E52 | F53: =F44+F52 | G53: =G44+G52 | H53: =H44+H52 | I53: =I44+I52 | ... O53: =O44+O52
A54: TOTAL EQUITY & LIABILITIES | B54: =B36+B53 | C54: =C36+C53 | D54: =D36+D53 | E54: =E36+E53 | F54: =F36+F53 | G54: =G36+G53 | H54: =H36+H53 | I54: =I36+I53 | ... O54: =O36+O53
A55: Balance check (Assets - E&L) | B55: =B32-B54 | C55: =C32-C54 | D55: =D32-D54 | E55: =E32-E54 | F55: =F32-F54 | G55: =G32-G54 | H55: =H32-H54 | I55: =I32-I54 | ... O55: =O32-O54

Sheet Integrated CF
A1: 23. INTEGRATED CASH FLOW STATEMENT (FY20A-FY33E)
A4: INR Crore unless stated | B4: FY20A | C4: FY21A | D4: FY22A | E4: FY23A | F4: FY24A | G4: FY25A | H4: FY26A | I4: FY27E | J4: FY28E | K4: FY29E | L4: FY30E | M4: FY31E | N4: FY32E | O4: FY33E
A5: Operating activities
A6: Profit after tax | I6: ='Integrated IS'!I25 | J6: ='Integrated IS'!J25 | K6: ='Integrated IS'!K25 | L6: ='Integrated IS'!L25 | M6: ='Integrated IS'!M25 | N6: ='Integrated IS'!N25 | O6: ='Integrated IS'!O25
A7: Add: Depreciation & amortisation | I7: ='Integrated IS'!I16 | J7: ='Integrated IS'!J16 | K7: ='Integrated IS'!K16 | L7: ='Integrated IS'!L16 | M7: ='Integrated IS'!M16 | N7: ='Integrated IS'!N16 | O7: ='Integrated IS'!O16
A8: Add: Finance costs | I8: ='Integrated IS'!I18 | J8: ='Integrated IS'!J18 | K8: ='Integrated IS'!K18 | L8: ='Integrated IS'!L18 | M8: ='Integrated IS'!M18 | N8: ='Integrated IS'!N18 | O8: ='Integrated IS'!O18
A9: Less: Increase in net working capital | I9: =-'Working Capital'!I12 | J9: =-'Working Capital'!J12 | K9: =-'Working Capital'!K12 | L9: =-'Working Capital'!L12 | M9: =-'Working Capital'!M12 | N9: =-'Working Capital'!N12 | O9: =-'Working Capital'!O12
A10: Net cash from operating activities | B10: ='Historical CF'!B5 | C10: ='Historical CF'!C5 | D10: ='Historical CF'!D5 | E10: ='Historical CF'!E5 | F10: ='Historical CF'!F5 | G10: ='Historical CF'!G5 | H10: ='Historical CF'!H5 | I10: =I6+I7+I8+I9 | J10: =J6+J7+J8+J9 | K10: =K6+K7+K8+K9 | L10: =L6+L7+L8+L9 | M10: =M6+M7+M8+M9 | N10: =N6+N7+N8+N9 | O10: =O6+O7+O8+O9
A11: Investing activities
A12: Capex | I12: =-'Capex Expansion'!I5 | J12: =-'Capex Expansion'!J5 | K12: =-'Capex Expansion'!K5 | L12: =-'Capex Expansion'!L5 | M12: =-'Capex Expansion'!M5 | N12: =-'Capex Expansion'!N5 | O12: =-'Capex Expansion'!O5
A13: Net cash used in investing activities | B13: ='Historical CF'!B7 | C13: ='Historical CF'!C7 | D13: ='Historical CF'!D7 | E13: ='Historical CF'!E7 | F13: ='Historical CF'!F7 | G13: ='Historical CF'!G7 | H13: ='Historical CF'!H7 | I13: =I12 | J13: =J12 | K13: =K12 | L13: =L12 | M13: =M12 | N13: =N12 | O13: =O12
A14: Financing activities
A15: Net debt drawdown/(repayment) | I15: ='Debt Schedule'!I7 | J15: ='Debt Schedule'!J7 | K15: ='Debt Schedule'!K7 | L15: ='Debt Schedule'!L7 | M15: ='Debt Schedule'!M7 | N15: ='Debt Schedule'!N7 | O15: ='Debt Schedule'!O7
A16: Interest paid | I16: =-'Integrated IS'!I18 | J16: =-'Integrated IS'!J18 | K16: =-'Integrated IS'!K18 | L16: =-'Integrated IS'!L18 | M16: =-'Integrated IS'!M18 | N16: =-'Integrated IS'!N18 | O16: =-'Integrated IS'!O18
A17: Dividends paid | I17: =-'Integrated IS'!I25*'Assumptions'!I36 | J17: =-'Integrated IS'!J25*'Assumptions'!I36 | K17: =-'Integrated IS'!K25*'Assumptions'!I36 | L17: =-'Integrated IS'!L25*'Assumptions'!I36 | M17: =-'Integrated IS'!M25*'Assumptions'!I36 | N17: =-'Integrated IS'!N25*'Assumptions'!I36 | O17: =-'Integrated IS'!O25*'Assumptions'!I36
A18: Lease principal payment | I18: =-'Lease Schedule'!I8 | J18: =-'Lease Schedule'!J8 | K18: =-'Lease Schedule'!K8 | L18: =-'Lease Schedule'!L8 | M18: =-'Lease Schedule'!M8 | N18: =-'Lease Schedule'!N8 | O18: =-'Lease Schedule'!O8
A19: Net cash from financing activities | B19: ='Historical CF'!B9 | C19: ='Historical CF'!C9 | D19: ='Historical CF'!D9 | E19: ='Historical CF'!E9 | F19: ='Historical CF'!F9 | G19: ='Historical CF'!G9 | H19: ='Historical CF'!H9 | I19: =I15+I16+I17+I18 | J19: =J15+J16+J17+J18 | K19: =K15+K16+K17+K18 | L19: =L15+L16+L17+L18 | M19: =M15+M16+M17+M18 | N19: =N15+N16+N17+N18 | O19: =O15+O16+O17+O18
A20: Net increase/(decrease) in cash | B20: =B10+B13+B19 | C20: =C10+C13+C19 | D20: =D10+D13+D19 | E20: =E10+E13+E19 | F20: =F10+F13+F19 | G20: =G10+G13+G19 | H20: =H10+H13+H19 | I20: =I10+I13+I19 | ... O20: =O10+O13+O19
A21: Opening cash | I21: ='Historical BS'!H25 | J21: =I22 | K21: =J22 | L21: =K22 | M21: =L22 | N21: =M22 | O21: =N22
A22: Closing cash | I22: =I21+I20 | J22: =J21+J20 | K22: =K21+K20 | L22: =L21+L20 | M22: =M21+M20 | N22: =N21+N20 | O22: =O21+O20

Sheet Scenario Analysis
A1: 24. SCENARIO ANALYSIS (Bear / Base / Bull)
A3: Base is linked to the live model. Bear/Bull are re-runs of the operating model with the assumption changes listed below (hardcoded results).
C4: Bear | D4: Base | E4: Bull
A5: Key assumption changes vs Base
A6: Occupancy delta (pp) | C6: -3.0 | D6: Base | E6: +2.0
A7: ARPOB growth delta (pp) | C7: -1.5 | D7: Base | E7: +1.0
A8: Bed-add factor | C8: 0.80x | D8: 1.00x | E8: 1.10x
A9: Cost ratio delta (pp) | C9: +0.5 | D9: Base | E9: -0.5
A10: Capex factor | C10: 1.05x | D10: 1.00x | E10: 1.00x
A11: FY33E outcomes (Rs Cr)
A12: Revenue (FY33E) | C12: 25052.64 | D12: ='Integrated IS'!O5 | E12: 36915.23
A13: EBITDA (FY33E) | C13: 6864.42 | D13: ='Integrated IS'!O13 | E13: 11591.38
A14: EBITDA margin (FY33E) | C14: 0.27 | D14: ='Integrated IS'!O14 | E14: 0.31
A15: PAT (FY33E) | C15: 4582.5 | D15: ='Integrated IS'!O25 | E15: 8363.29
A16: Valuation
A17: DCF Target price (Gordon, Rs) | C17: 382.62 | D17: ='DCF'!C33 | E17: 755.38
A18: Current market price (Rs) | C18: ='Assumptions'!I43 | D18: ='Assumptions'!I43 | E18: ='Assumptions'!I43

Sheet DCF
A1: 25. DCF VALUATION (FCFF)
A3: WACC build-up
A4: Risk-free rate | C4: ='Assumptions'!I38
A5: Equity risk premium | C5: ='Assumptions'!I39
A6: Beta | C6: ='Assumptions'!I40
A7: Cost of equity (CAPM) | C7: =C4+C6*C5
A8: Pre-tax cost of debt | C8: ='Assumptions'!I41
A9: Tax rate | C9: ='Assumptions'!I35
A10: Market cap (Rs Cr) = price x shares | C10: ='Assumptions'!I43*'Assumptions'!I44
A11: Gross debt FY26 (Rs Cr) | C11: ='Historical BS'!H38+'Historical BS'!H46
A12: Weight of equity | C12: =C10/(C10+C11)
A13: Weight of debt | C13: =C11/(C10+C11)
A14: WACC | C14: =C12*C7+C13*C8*(1-C9)
A15: Terminal growth rate | C15: ='Assumptions'!I42
A16: INR Crore unless stated | B16: FY20A | C16: FY21A | D16: FY22A | E16: FY23A | F16: FY24A | G16: FY25A | H16: FY26A | I16: FY27E | J16: FY28E | K16: FY29E | L16: FY30E | M16: FY31E | N16: FY32E | O16: FY33E
A17: EBIT | I17: ='Integrated IS'!I17 | J17: ='Integrated IS'!J17 | K17: ='Integrated IS'!K17 | L17: ='Integrated IS'!L17 | M17: ='Integrated IS'!M17 | N17: ='Integrated IS'!N17 | O17: ='Integrated IS'!O17
A18: NOPAT = EBIT x (1-t) | I18: =I17*(1-$C$9) | J18: =J17*(1-$C$9) | K18: =K17*(1-$C$9) | L18: =L17*(1-$C$9) | M18: =M17*(1-$C$9) | N18: =N17*(1-$C$9) | O18: =O17*(1-$C$9)
A19: Add: D&A | I19: ='Integrated IS'!I16 | J19: ='Integrated IS'!J16 | K19: ='Integrated IS'!K16 | L19: ='Integrated IS'!L16 | M19: ='Integrated IS'!M16 | N19: ='Integrated IS'!N16 | O19: ='Integrated IS'!O16
A20: Less: Capex | I20: =-'Capex Expansion'!I5 | J20: =-'Capex Expansion'!J5 | K20: =-'Capex Expansion'!K5 | L20: =-'Capex Expansion'!L5 | M20: =-'Capex Expansion'!M5 | N20: =-'Capex Expansion'!N5 | O20: =-'Capex Expansion'!O5
A21: Less: Increase in NWC | I21: =-'Working Capital'!I12 | J21: =-'Working Capital'!J12 | K21: =-'Working Capital'!K12 | L21: =-'Working Capital'!L12 | M21: =-'Working Capital'!M12 | N21: =-'Working Capital'!N12 | O21: =-'Working Capital'!O12
A22: Free cash flow to firm (FCFF) | I22: =I18+I19+I20+I21 | J22: =J18+J19+J20+J21 | K22: =K18+K19+K20+K21 | L22: =L18+L19+L20+L21 | M22: =M18+M19+M20+M21 | N22: =N18+N19+N20+N21 | O22: =O18+O19+O20+O21
A23: Discount period | I23: 1 | J23: 2 | K23: 3 | L23: 4 | M23: 5 | N23: 6 | O23: 7
A24: Discount factor | I24: =1/(1+$C$14)^I23 | J24: =1/(1+$C$14)^J23 | K24: =1/(1+$C$14)^K23 | L24: =1/(1+$C$14)^L23 | M24: =1/(1+$C$14)^M23 | N24: =1/(1+$C$14)^N23 | O24: =1/(1+$C$14)^O23
A25: PV of FCFF | I25: =I22*I24 | J25: =J22*J24 | K25: =K22*K24 | L25: =L22*L24 | M25: =M22*M24 | N25: =N22*N24 | O25: =O22*O24
A26: Valuation output (Rs Cr)
A27: Sum of PV of explicit FCFF (FY27-33) | C27: =SUM(I25:O25)
A28: Terminal value (Gordon): FCFF_FY33 x (1+g)/(WACC-g) | C28: =O22*(1+C15)/(C14-C15)
A29: PV of terminal value | C29: =C28/(1+C14)^7
A30: Enterprise value | C30: =C27+C29
A31: Less: Net debt (FY26) | C31: ='Assumptions'!I45
A32: Equity value | C32: =C30-C31
A33: Target price / share (Rs) - Gordon | C33: =C32/'Assumptions'!I44
A34: Terminal value (Exit multiple): EBITDA_FY33 x exit x | C34: ='Integrated IS'!O13*'Assumptions'!I48
A35: PV of terminal value (exit) | C35: =C34/(1+C14)^7
A36: Enterprise value (exit multiple) | C36: =C27+C35
A37: Equity value (exit multiple) | C37: =C36-C31
A38: Target price / share (Rs) - Exit multiple | C38: =C37/'Assumptions'!I44
A39: Current market price (Rs) | C39: ='Assumptions'!I43

Sheet Relative Valuation
A1: 26. RELATIVE VALUATION & PEER COMPARISON
A3: Peer data: NSE/moneycontrol/tipranks (Jul-2026). Mcap Rs Cr, P/E TTM. EV/EBITDA & operating metrics are market/analyst estimates (blue = input).
A4: Company | B4: Mkt Cap (Cr) | C4: P/E (TTM) | D4: EV/EBITDA (FY27E) | E4: Rev gth | F4: EBITDA mgn | G4: ROCE | H4: Net Debt/EBITDA | I4: ARPOB (Rs 000) | J4: Occupancy
A5: Max Healthcare | B5: 101503 | C5: 73.1 | D5: 41 | E5: 0.19 | F5: 0.268 | G5: 0.127 | H5: 0.9 | I5: 76 | J5: 0.747
A6: Apollo Hospitals | B6: 112195 | C6: 68 | D6: 28 | E6: 0.16 | F6: 0.15 | G6: 0.16 | H6: 1 | I6: 60 | J6: 0.66
A7: Fortis Healthcare | B7: 66572 | C7: 68.4 | D7: 26 | E7: 0.13 | F7: 0.19 | G7: 0.12 | H7: 0.3 | I7: 66 | J7: 0.68
A8: Global Health (Medanta) | B8: 29707 | C8: 66.6 | D8: 25 | E8: 0.16 | F8: 0.24 | G8: 0.18 | H8: -0.2 | I8: 66 | J8: 0.62
A9: Narayana Hrudayalaya | B9: 35773 | C9: 50 | D9: 20 | E9: 0.12 | F9: 0.22 | G9: 0.2 | H9: 0.1 | I9: 42 | J9: 0.58
A10: Aster DM Healthcare | B10: 34481 | C10: 60 | D10: 18 | E10: 0.14 | F10: 0.17 | G10: 0.13 | H10: 0.6 | I10: 40 | J10: 0.65
A12: Max Healthcare implied valuation (on FY27E)
A13: FY27E PBIDT (Rs Cr) | C13: ='Integrated IS'!I15
A14: FY27E EPS (Rs) | C14: ='Integrated IS'!I27
A15: Target EV/EBITDA (x) | C15: ='Assumptions'!I46
A16: Implied EV (Rs Cr) | C16: =C13*C15
A17: Target price - EV/EBITDA (Rs) | C17: =(C16-'Assumptions'!I45)/'Assumptions'!I44
A18: Target P/E (x) | C18: ='Assumptions'!I47
A19: Target price - P/E (Rs) | C19: =C18*C14
A20: Current market price (Rs) | C20: ='Assumptions'!I43
A22: Premium justification: Max commands highest ARPOB (Rs76k vs peers Rs40-66k), industry-leading occupancy (~75%) and EBITDA/bed, premium Delhi-NCR/metro mix, strong ROCE and near-zero net leverage. Offsetting: valuation already rich (41x FY27E EV/EBITDA vs peers 18-28x).

Sheet SoTP Street
A1: 26b. SOTP & STREET VALUATION (12-month forward basis, FY28E)
A3: Sum-of-the-parts on 12-month-forward (FY28E) segment economics, mirroring sell-side methodology (e.g. Motilal Oswal: ~35x hospitals, 30x Max Lab, EV/sales for Max@Home). Multiples are blue inputs.
A5: Inputs (FY28E, Rs Cr)
A6: Total EBITDA (FY28E) | C6: ='Integrated IS'!J13
A7: Max Lab revenue (FY28E) | C7: ='Revenue Build'!J9
A8: Max Lab EBITDA margin (input) | C8: 0.18
A9: Max Lab EBITDA | C9: =C7*C8
A10: Max@Home revenue (FY28E) | C10: ='Revenue Build'!J10
A11: Hospital & other EBITDA (bal.) | C11: =C6-C9
A12: Multiples (blue = input)
A13: Hospital EV/EBITDA (x) | C13: 34
A14: Max Lab EV/EBITDA (x) | C14: 30
A15: Max@Home EV/Sales (x) | C15: 9
A16: Enterprise & equity value (Rs Cr)
A17: Hospital EV | C17: =C11*C13
A18: Max Lab EV | C18: =C9*C14
A19: Max@Home EV | C19: =C10*C15
A20: Total Enterprise Value | C20: =C17+C18+C19
A21: Less: Net debt (fwd, FY27E) | C21: ='Debt Schedule'!I6-'Integrated BS'!I25
A22: Equity value | C22: =C20-C21
A23: SoTP target price / share (Rs) | C23: =C22/'Assumptions'!I44
A24: Current market price (Rs) | C24: ='Assumptions'!I43
A25: Upside / (downside) | C25: =C23/C24-1
A26: Valuation summary - methods (Rs/share)
A27: SoTP (12M forward, FY28E) | C27: =C23
A28: Relative EV/EBITDA (FY27E) | C28: ='Relative Valuation'!C17
A29: Relative P/E (FY27E) | C29: ='Relative Valuation'!C19
A30: DCF - exit multiple (22x) | C30: ='DCF'!C38
A31: DCF - Gordon (downside anchor) | C31: ='DCF'!C33
A32: Blended target (SoTP + Exit-multiple DCF) | C32: =AVERAGE(C23,'DCF'!C38) | D32: =C32/'Assumptions'!I43-1
A33: Recent broker views (external, Feb-Jul 2026)
A34: Broker | B34: Rating | C34: Target (Rs) | D34: Date
A35: Broker | B35: Rating | C35: Target (Rs) | D35: Date/Note
A36: Motilal Oswal | B36: BUY | C36: 1,270-1,360 | D36: Feb/Nov-2026; SoTP 35x fwd hosp
A37: Anand Rathi | B37: BUY | C37: 1,300 | D37: Feb-2026
A38: Nuvama | B38: BUY | C38: 1,023 | D38: post-Q4
A39: Jefferies | B39: BUY | C39: ~25% upside | D39: 2026
A40: Consensus (26 analysts, S&P) | B40: BUY | C40: 1,148 (avg); range 615-1,400 | D40: Jul-2026
A42: Source: moneycontrol, ET Now, Business Today, stockanalysis.com (S&P Global consensus), TradingView (Jul-2026). Content rephrased for licensing compliance.

Sheet Sensitivity
A1: 27. SENSITIVITY - DCF Target Price (Gordon): WACC x Terminal Growth
A3: Target price (Rs/share) = (NPV(WACC, FCFF FY27-33) + PV of Gordon terminal value - net debt) / shares
B5: Terminal growth ->
A6: WACC v | C6: 0.045 | D6: 0.05 | E6: 0.055 | F6: 0.06 | G6: 0.065
B7: 0.105 | C7: =(NPV(0.105,'DCF'!$I$22:$O$22)+('DCF'!$O$22*(1+0.045)/(0.105-0.045))/(1+0.105)^7-'Assumptions'!I45)/'Assumptions'!I44 | D7: =(NPV(0.105,'DCF'!$I$22:$O$22)+('DCF'!$O$22*(1+0.05)/(0.105-0.05))/(1+0.105)^7-'Assumptions'!I45)/'Assumptions'!I44 | E7: =(NPV(0.105,'DCF'!$I$22:$O$22)+('DCF'!$O$22*(1+0.055)/(0.105-0.055))/(1+0.105)^7-'Assumptions'!I45)/'Assumptions'!I44 | F7: =(NPV(0.105,'DCF'!$I$22:$O$22)+('DCF'!$O$22*(1+0.06)/(0.105-0.06))/(1+0.105)^7-'Assumptions'!I45)/'Assumptions'!I44 | G7: =(NPV(0.105,'DCF'!$I$22:$O$22)+('DCF'!$O$22*(1+0.065)/(0.105-0.065))/(1+0.105)^7-'Assumptions'!I45)/'Assumptions'!I44
B8: 0.11 | C8: =(NPV(0.11,'DCF'!$I$22:$O$22)+('DCF'!$O$22*(1+0.045)/(0.11-0.045))/(1+0.11)^7-'Assumptions'!I45)/'Assumptions'!I44 | D8: =(NPV(0.11,'DCF'!$I$22:$O$22)+('DCF'!$O$22*(1+0.05)/(0.11-0.05))/(1+0.11)^7-'Assumptions'!I45)/'Assumptions'!I44 | E8: =(NPV(0.11,'DCF'!$I$22:$O$22)+('DCF'!$O$22*(1+0.055)/(0.11-0.055))/(1+0.11)^7-'Assumptions'!I45)/'Assumptions'!I44 | F8: =(NPV(0.11,'DCF'!$I$22:$O$22)+('DCF'!$O$22*(1+0.06)/(0.11-0.06))/(1+0.11)^7-'Assumptions'!I45)/'Assumptions'!I44 | G8: =(NPV(0.11,'DCF'!$I$22:$O$22)+('DCF'!$O$22*(1+0.065)/(0.11-0.065))/(1+0.11)^7-'Assumptions'!I45)/'Assumptions'!I44
B9: 0.115 | C9: =(NPV(0.115,'DCF'!$I$22:$O$22)+('DCF'!$O$22*(1+0.045)/(0.115-0.045))/(1+0.115)^7-'Assumptions'!I45)/'Assumptions'!I44 | D9: =(NPV(0.115,'DCF'!$I$22:$O$22)+('DCF'!$O$22*(1+0.05)/(0.115-0.05))/(1+0.115)^7-'Assumptions'!I45)/'Assumptions'!I44 | E9: =(NPV(0.115,'DCF'!$I$22:$O$22)+('DCF'!$O$22*(1+0.055)/(0.115-0.055))/(1+0.115)^7-'Assumptions'!I45)/'Assumptions'!I44 | F9: =(NPV(0.115,'DCF'!$I$22:$O$22)+('DCF'!$O$22*(1+0.06)/(0.115-0.06))/(1+0.115)^7-'Assumptions'!I45)/'Assumptions'!I44 | G9: =(NPV(0.115,'DCF'!$I$22:$O$22)+('DCF'!$O$22*(1+0.065)/(0.115-0.065))/(1+0.115)^7-'Assumptions'!I45)/'Assumptions'!I44
B10: 0.12 | C10: =(NPV(0.12,'DCF'!$I$22:$O$22)+('DCF'!$O$22*(1+0.045)/(0.12-0.045))/(1+0.12)^7-'Assumptions'!I45)/'Assumptions'!I44 | D10: =(NPV(0.12,'DCF'!$I$22:$O$22)+('DCF'!$O$22*(1+0.05)/(0.12-0.05))/(1+0.12)^7-'Assumptions'!I45)/'Assumptions'!I44 | E10: =(NPV(0.12,'DCF'!$I$22:$O$22)+('DCF'!$O$22*(1+0.055)/(0.12-0.055))/(1+0.12)^7-'Assumptions'!I45)/'Assumptions'!I44 | F10: =(NPV(0.12,'DCF'!$I$22:$O$22)+('DCF'!$O$22*(1+0.06)/(0.12-0.06))/(1+0.12)^7-'Assumptions'!I45)/'Assumptions'!I44 | G10: =(NPV(0.12,'DCF'!$I$22:$O$22)+('DCF'!$O$22*(1+0.065)/(0.12-0.065))/(1+0.12)^7-'Assumptions'!I45)/'Assumptions'!I44
B11: 0.125 | C11: =(NPV(0.125,'DCF'!$I$22:$O$22)+('DCF'!$O$22*(1+0.045)/(0.125-0.045))/(1+0.125)^7-'Assumptions'!I45)/'Assumptions'!I44 | D11: =(NPV(0.125,'DCF'!$I$22:$O$22)+('DCF'!$O$22*(1+0.05)/(0.125-0.05))/(1+0.125)^7-'Assumptions'!I45)/'Assumptions'!I44 | E11: =(NPV(0.125,'DCF'!$I$22:$O$22)+('DCF'!$O$22*(1+0.055)/(0.125-0.055))/(1+0.125)^7-'Assumptions'!I45)/'Assumptions'!I44 | F11: =(NPV(0.125,'DCF'!$I$22:$O$22)+('DCF'!$O$22*(1+0.06)/(0.125-0.06))/(1+0.125)^7-'Assumptions'!I45)/'Assumptions'!I44 | G11: =(NPV(0.125,'DCF'!$I$22:$O$22)+('DCF'!$O$22*(1+0.065)/(0.125-0.065))/(1+0.125)^7-'Assumptions'!I45)/'Assumptions'!I44
B12: 0.13 | C12: =(NPV(0.13,'DCF'!$I$22:$O$22)+('DCF'!$O$22*(1+0.045)/(0.13-0.045))/(1+0.13)^7-'Assumptions'!I45)/'Assumptions'!I44 | D12: =(NPV(0.13,'DCF'!$I$22:$O$22)+('DCF'!$O$22*(1+0.05)/(0.13-0.05))/(1+0.13)^7-'Assumptions'!I45)/'Assumptions'!I44 | E12: =(NPV(0.13,'DCF'!$I$22:$O$22)+('DCF'!$O$22*(1+0.055)/(0.13-0.055))/(1+0.13)^7-'Assumptions'!I45)/'Assumptions'!I44 | F12: =(NPV(0.13,'DCF'!$I$22:$O$22)+('DCF'!$O$22*(1+0.06)/(0.13-0.06))/(1+0.13)^7-'Assumptions'!I45)/'Assumptions'!I44 | G12: =(NPV(0.13,'DCF'!$I$22:$O$22)+('DCF'!$O$22*(1+0.065)/(0.13-0.065))/(1+0.13)^7-'Assumptions'!I45)/'Assumptions'!I44
A14: Base case: WACC 12.0%, terminal growth 5.5%. Note: pure-Gordon DCF is conservative; exit-multiple DCF (22x) and relative valuation give higher fair values (see DCF & Relative Valuation sheets).

Sheet Source Log
A1: 28. SOURCE & ASSUMPTION LOG
A3: Assumption / Data | B3: Value | C3: Source Type | D3: Source | E3: Report/Ref | F3: Pg/Note | G3: Date | H3: Justification
A4: FY26 Revenue Rs8,373 Cr | B4: 8,373 | C4: Annual Report | D4: MHIL AR FY26 - Note 27 | E4: FY26 AR | F4: p501 | G4: May-2026 | H4: Reported consolidated revenue from operations
A5: FY26 PBIDT margin 28.2% | B5: 28.2% | C5: Annual Report | D5: MHIL AR FY26 MD&A | E5: FY26 AR | F5: p220 | G5: May-2026 | H5: Management-reported PBIDT margin on total income
A6: ARPOB Rs76k / 77.9k (Q4) | B6: 76-78 | C6: Annual Report/Concall | D6: AR FY26 MD&A; Q4FY26 call | E6: FY26 | F6: p223 | G6: May-2026 | H6: Basis for ARPOB growth assumption
A7: Operational beds 3,841 | B7: 3,841 | C7: Annual Report | D7: AR FY26 operational metrics | E7: FY26 AR | F7: p223 | G7: May-2026 | H7: Base for bed capacity schedule
A8: Occupancy ~74.7% | B8: 74.7% | C8: Annual Report/CARE | D8: AR FY26; CARE report | E8: FY26 | F8: p223 | G8: Oct-2025 | H8: Industry-leading occupancy
A9: Bed pipeline (Gurgaon 500 etc.) | B9: see AR | C9: Concall/AR | D9: Q4FY26 concall; AR pipeline | E9: FY26 | F9: - | G9: May-2026 | H9: Bed-addition schedule driver
A10: Growth capex FY27-30 Rs6,672 Cr | B10: 6,672 | C10: Annual Report | D10: AR FY26 pipeline table | E10: FY26 | F10: - | G10: May-2026 | H10: Capex schedule driver
A11: Credit rating CARE AA+/Stable | B11: AA+ | C11: Credit Rating | D11: CARE Ratings press release | E11: Rating 2025 | F11: - | G11: Oct-2025 | H11: Low cost of debt; net leverage <1.5x guardrail
A12: Net leverage guardrail <1.5x | B12: 1.43x | C12: Credit Rating | D12: CARE Ratings | E12: Rating 2025 | F12: - | G12: Oct-2025 | H12: Debt schedule sizing / covenant cross-check
A13: Normalised tax rate 24% | B13: 24% | C13: Annual Report | D13: AR FY24-FY26 | E13: FY24-26 | F13: Note 16 | G13: - | H13: FY26 ETR distorted by one-time DTA gain Rs141 Cr
A14: Max Lab Rs201 Cr (+15%) | B14: 201 | C14: Annual Report | D14: AR FY26 MD&A | E14: FY26 AR | F14: p87 | G14: May-2026 | H14: Segment revenue growth
... A19: Peer multiples | B19: see sheet | C19: External | D19: moneycontrol/tipranks | E19: - | F19: - | G19: Jul-2026 | H19: Relative valuation benchmarking

Sheet Guidance Tracker
A1: 29. MANAGEMENT GUIDANCE TRACKER
A3: Date/Source | B3: Management statement | C3: KPI/Metric | D3: Expected outcome | E3: Actual outcome | F3: Assessment
A4: FY24 AR / call | B4: Revenue growth 12-14% in FY25 on stable occupancy & ARPOB | C4: Revenue growth | D4: 12-14% (organic guidance) | E4: FY25 +30% (incl. Jaypee/Sahara acq.) | F4: Beat (inorganic-led)
A5: Ongoing | B5: Double bed capacity in ~4-5 years (organic + inorganic) | C5: Beds | D5: ~14,500 network beds | E5: On track: 6,131 network; pipeline firmed | F5: Credible
A6: Q4FY26 call | B6: New brownfield beds to ramp with operating leverage as occupancy builds | C6: EBITDA margin | D6: Margin recovery medium-term | E6: FY26 PBIDT margin 28.2% (stable) | F6: In line
A7: Q4FY26 call | B7: Sector-56 Gurgaon (500 beds) to commission by end FY27 | C7: Bed additions | D7: +500 beds FY27 | E7: In progress (interior/facade started) | F7: On track
A8: Q4FY26 call | B8: Occupancy sustained >75% despite new capacity | C8: Occupancy | D8: ~75% | E8: FY26 74.7% (network >75%) | F8: In line
A9: Q4FY26 call | B9: Oncology onco-drug discounting drags ARPOB near-term; other specialties to fill | C9: ARPOB/case-mix | D9: Normalise as mix shifts | E9: ARPOB Rs77.9k Q4 (resilient) | F9: Monitor
A10: CARE Oct-2025 | B10: PBILDT margin to sustain >25% through expansion | C10: EBITDA margin | D10: greater than 25% | E10: FY26 26-28% | F10: In line
A11: CARE Oct-2025 | B11: Net leverage to stay <1.5x despite capex | C11: Net Debt/EBITDA | D11: <1.5x | E11: FY26 <1x (network) | F11: Comfortable
A13: Assessment: management has a credible track record on capacity build-out, occupancy discipline and margin sustenance; guidance is generally met or beaten (often via well-integrated M&A). Forward guidance treated as reliable in the base case.

Sheet Model Checks
A1: 30. MODEL CHECKS & QUALITY CONTROL
C3: Result | D3: Max error
A4: Balance sheet balances (Assets = E&L) | C4: =IF(ABS(D4)<0.5,"OK","ERROR") | D4: =SUMPRODUCT(ABS('Integrated BS'!$I$55:$O$55))
A5: Cash flow closing cash = BS cash | C5: =IF(ABS(D5)<0.5,"OK","ERROR") | D5: =SUMPRODUCT(ABS('Integrated CF'!$I$22:$O$22-'Integrated BS'!$I$25:$O$25))
A6: PPE roll-forward ties to BS | C6: =IF(ABS(D6)<0.5,"OK","ERROR") | D6: ='Integrated BS'!$O$6-'PPE Depreciation'!$O$9
A7: Debt roll-forward ties to BS | C7: =IF(ABS(D7)<0.5,"OK","ERROR") | D7: =('Integrated BS'!$O$38+'Integrated BS'!$O$46)-'Debt Schedule'!$O$6
A8: Revenue: IS = Revenue Build (FY27) | C8: =IF(ABS(D8)<0.5,"OK","ERROR") | D8: ='Integrated IS'!$I$5-'Revenue Build'!$I$12
A9: EBITDA: IS = EBITDA Build (FY30) | C9: =IF(ABS(D9)<0.5,"OK","ERROR") | D9: ='Integrated IS'!$L$13-'EBITDA Build'!$L$11
A10: Depreciation: IS = PPE schedule (FY29) | C10: =IF(ABS(D10)<0.5,"OK","ERROR") | D10: ='Integrated IS'!$K$16-'PPE Depreciation'!$K$18
A11: Working capital ties to BS receivables (FY31) | C11: =IF(ABS(D11)<0.5,"OK","ERROR") | D11: ='Integrated BS'!$M$24-'Working Capital'!$M$6
A12: Historical BS balances (FY20-26) | C12: =IF(ABS(D12)<0.5,"OK","ERROR") | D12: =SUMPRODUCT(ABS('Historical BS'!$B$55:$H$55))
A13: Colour coding: BLUE = hardcoded input | BLACK = same-sheet calculation | GREEN = cross-sheet link.
A14: No circular references: interest is computed on average scheduled debt (drawdowns/repayments are inputs, not cash-sweep). Cash flows from the CF statement into BS cash.
